Workbook

Sheet Plan
B1: Plantilla de estimacion y seguimiento Scrum | V1: Versión | W1: 2.14 | X1: 2.14 Scrum
B2: Fase | C2: Actividad | D2: Minutos Estimados | M2: Minutos Reales
D4: Líder/SM | E4: Product Owner | F4: Planif. | G4: Desarrollo | H4: Cambios | I4: Calidad | J4: Total | K4: Acumulado | L4: Semana Estimada | M4: Líder/SM | N4: Product Owner | O4: Planif. | P4: Desarrollo | Q4: Cambios | R4: Calidad | S4: Total | T4: Acumulado | U4: Semana Fin | V4: Estado | Y4: Asignación de roles
B5: Lanzamiento | C5: Asignar equipos y roles | D5: 10 | E5: 10 | F5: 10 | G5: 10 | H5: 10 | I5: 10 | J5: =IF(SUM(D5:I5)=0,"",SUM(D5:I5)) -> 60 | K5: =SUM($J$5:J5) -> 60 | L5: 1 | M5: 10 | N5: 10 | O5: 10 | P5: 10 | Q5: 10 | R5: 10 | S5: =SUM(M5:R5) -> 60 | T5: =SUM($S$5:S5) -> 60 | U5: 1 | V5: Completada | Y5: Rol | Z5: Persona asignada | AA5: Columnas esfuerzo
B6: Lanzamiento | C6: Definir proceso de reuniones | D6: 20 | E6: 20 | F6: 20 | G6: 20 | H6: 20 | I6: 20 | J6: =IF(SUM(D6:I6)=0,"",SUM(D6:I6)) -> 120 | K6: =SUM($J$5:J6) -> 180 | L6: 1 | M6: 20 | N6: 20 | O6: 20 | P6: 20 | Q6: 20 | R6: 20 | S6: =SUM(M6:R6) -> 120 | T6: =SUM($S$5:S6) -> 180 | U6: 1 | V6: Completada | Y6: Líder / Scrum Master | Z6: Santi | AA6: Estim. D / Real M
B7: Lanzamiento | C7: Realizar Estándar de Documentación | E7: 20 | J7: =IF(SUM(D7:I7)=0,"",SUM(D7:I7)) -> 20 | K7: =SUM($J$5:J7) -> 200 | L7: 1 | N7: 30 | R7: 20 | S7: =SUM(M7:R7) -> 50 | T7: =SUM($S$5:S7) -> 230 | U7: 2 | V7: Completada | Y7: Product Owner | Z7: Joaquin | AA7: Estim. E / Real N
B8: Lanzamiento | C8: Realizar Estándar de Agendas | D8: 10 | E8: 10 | F8: 10 | G8: 10 | H8: 10 | I8: 10 | J8: =IF(SUM(D8:I8)=0,"",SUM(D8:I8)) -> 60 | K8: =SUM($J$5:J8) -> 260 | L8: 1 | M8: 20 | N8: 20 | O8: 15 | P8: 15 | Q8: 15 | R8: 10 | S8: =SUM(M8:R8) -> 95 | T8: =SUM($S$5:S8) -> 325 | U8: 1 | V8: Completada | Y8: Planificación | Z8: Pablo | AA8: Estim. F / Real O
B9: Lanzamiento | C9: Realizar Estándar de Actas | D9: 20 | J9: =IF(SUM(D9:I9)=0,"",SUM(D9:I9)) -> 20 | K9: =SUM($J$5:J9) -> 280 | L9: 1 | M9: 20 | S9: =SUM(M9:R9) -> 20 | T9: =SUM($S$5:S9) -> 345 | U9: 3 | V9: Completada | Y9: Desarrollo | Z9: Victor | AA9: Estim. G / Real P
B10: Lanzamiento | C10: Definir Ciclo de Vida a aplicar (actividades) | D10: 10 | E10: 10 | F10: 10 | G10: 10 | H10: 10 | I10: 10 | J10: =IF(SUM(D10:I10)=0,"",SUM(D10:I10)) -> 60 | K10: =SUM($J$5:J10) -> 340 | L10: 1 | M10: 15 | N10: 15 | O10: 15 | P10: 15 | Q10: 15 | R10: 10 | S10: =SUM(M10:R10) -> 85 | T10: =SUM($S$5:S10) -> 430 | U10: 1 | V10: Completada | Y10: Cambios | Z10: Carlos | AA10: Estim. H / Real Q
B11: Lanzamiento | C11: Definir outputs y plantillas del CV | D11: 15 | J11: =IF(SUM(D11:I11)=0,"",SUM(D11:I11)) -> 15 | K11: =SUM($J$5:J11) -> 355 | L11: 1 | M11: 20 | S11: =SUM(M11:R11) -> 20 | T11: =SUM($S$5:S11) -> 450 | U11: 3 | V11: Completada | Y11: Calidad | Z11: Miguel | AA11: Estim. I / Real R
B12: Lanzamiento | C12: Definir Entorno de Desarrollo | D12: 15 | E12: 15 | F12: 15 | G12: 15 | H12: 15 | I12: 15 | J12: =IF(SUM(D12:I12)=0,"",SUM(D12:I12)) -> 90 | K12: =SUM($J$5:J12) -> 445 | L12: 1 | M12: 20 | N12: 20 | O12: 20 | P12: 20 | Q12: 10 | R12: 15 | S12: =SUM(M12:R12) -> 105 | T12: =SUM($S$5:S12) -> 555 | U12: 1 | V12: Completada | Y12: Celdas amarillas: persona asignada. El orden de columnas es el de D4:I4 y M4:R4. | Z12: Estim. U / Real V
B13: Lanzamiento | C13: Configurar Entorno de Desarrollo | D13: 45 | E13: 45 | F13: 45 | G13: 45 | H13: 45 | I13: 45 | J13: =IF(SUM(D13:I13)=0,"",SUM(D13:I13)) -> 270 | K13: =SUM($J$5:J13) -> 715 | L13: 1 | M13: 150 | S13: =SUM(M13:R13) -> 150 | T13: =SUM($S$5:S13) -> 705 | U13: 2 | V13: Completada
B14: Lanzamiento | C14: Definir Estándar de Codificación | D14: 45 | E14: 45 | F14: 45 | G14: 45 | H14: 45 | I14: 45 | J14: =IF(SUM(D14:I14)=0,"",SUM(D14:I14)) -> 270 | K14: =SUM($J$5:J14) -> 985 | L14: 1 | M14: 15 | N14: 15 | O14: 15 | P14: 15 | Q14: 10 | R14: 10 | S14: =SUM(M14:R14) -> 80 | T14: =SUM($S$5:S14) -> 785 | U14: 2 | V14: Completada | Y14: Esfuerzo Sprint1 | Z14: =6*43 -> 258 | AA14: Horas
B15: Lanzamiento | C15: Introducir datos de Planificación/Monitorización S1 (esfuerzo real / semana) | D15: 5 | E15: 5 | F15: 5 | G15: 5 | H15: 5 | I15: 5 | J15: =IF(SUM(D15:I15)=0,"",SUM(D15:I15)) -> 30 | K15: =SUM($J$5:J15) -> 1015 | L15: 1 | M15: 5 | N15: 5 | O15: 5 | P15: 5 | Q15: 5 | R15: 5 | S15: =SUM(M15:R15) -> 30 | T15: =SUM($S$5:S15) -> 815 | U15: 1 | V15: Completada | Y15: M&M (10%) | Z15: 30 | AA15: Minutos
J16: =IF(SUM(D16:I16)=0,"",SUM(D16:I16))
J17: =IF(SUM(D17:I17)=0,"",SUM(D17:I17))
J18: =IF(SUM(D18:I18)=0,"",SUM(D18:I18))
B19: Requisitos | C19: Obtener Historias de Usuario (US) | D19: 25 | E19: 25 | F19: 25 | G19: 25 | J19: =IF(SUM(D19:I19)=0,"",SUM(D19:I19)) -> 100 | K19: =SUM($J$5:J19) -> 1115 | L19: 2 | M19: 30 | N19: 30 | O19: 30 | P19: 30 | S19: =SUM(M19:R19) -> 120 | T19: =SUM($S$5:S19) -> 935 | U19: 3 | V19: Completada | Y19: Total Roles
B20: Requisitos | C20: Describir las US según plantilla (Como/Quiero/Para + criterios de aceptación) | D20: 5 | E20: 5 | F20: 5 | G20: 5 | J20: =IF(SUM(D20:I20)=0,"",SUM(D20:I20)) -> 20 | K20: =SUM($J$5:J20) -> 1135 | L20: 3 | M20: 5 | N20: 5 | O20: 5 | P20: 5 | S20: =SUM(M20:R20) -> 20 | T20: =SUM($S$5:S20) -> 955 | U20: 3 | V20: Completada | Y20: Rol | Z20: Minutos Estimados | AA20: Horas Estimadas | AB20: Minutos Reales | AC20: Horas Reales
B21: Requisitos | C21: Completar campos de US para puntos de función | E21: 120 | G21: 120 | J21: =IF(SUM(D21:I21)=0,"",SUM(D21:I21)) -> 240 | K21: =SUM($J$5:J21) -> 1375 | L21: 3 | N21: 45 | P21: 180 | S21: =SUM(M21:R21) -> 225 | T21: =SUM($S$5:S21) -> 1180 | U21: 4 | V21: Completada | Y21: Líder / Scrum Master | Z21: =SUM(D:D) -> 1980 | AA21: =Z21/60 -> 33 | AB21: =SUM(M:M) -> 590 | AC21: =AB21/60 -> 9.8333333
B22: Requisitos | C22: Elaborar Product Backlog priorizado | D22: 10 | E22: 10 | F22: 10 | G22: 10 | J22: =IF(SUM(D22:I22)=0,"",SUM(D22:I22)) -> 40 | K22: =SUM($J$5:J22) -> 1415 | L22: 3 | M22: 10 | N22: 10 | O22: 10 | P22: 10 | S22: =SUM(M22:R22) -> 40 | T22: =SUM($S$5:S22) -> 1220 | U22: 3 | V22: Completada | Y22: Product Owner | Z22: =SUM(E:E) -> 1970 | AA22: =Z22/60 -> 32.833333 | AB22: =SUM(N:N) -> 675 | AC22: =AB22/60 -> 11.25
B23: Requisitos | C23: Inspeccionar las US y criterios de aceptacion (Q) | D23: 30 | E23: 30 | F23: 30 | G23: 30 | J23: =IF(SUM(D23:I23)=0,"",SUM(D23:I23)) -> 120 | K23: =SUM($J$5:J23) -> 1535 | L23: 3 | M23: 60 | N23: 60 | O23: 60 | P23: 60 | S23: =SUM(M23:R23) -> 240 | T23: =SUM($S$5:S23) -> 1460 | U23: 4 | V23: Completada | Y23: Planificación | Z23: =SUM(F:F) -> 1815 | AA23: =Z23/60 -> 30.25 | AB23: =SUM(O:O) -> 505 | AC23: =AB23/60 -> 8.4166667
B24: Requisitos | C24: Poner en línea base las US (GCS) | D24: 5 | E24: 5 | F24: 5 | G24: 5 | J24: =IF(SUM(D24:I24)=0,"",SUM(D24:I24)) -> 20 | K24: =SUM($J$5:J24) -> 1555 | L24: 3 | M24: 5 | N24: 5 | O24: 5 | P24: 5 | S24: =SUM(M24:R24) -> 20 | T24: =SUM($S$5:S24) -> 1480 | U24: 4 | V24: Completada | Y24: Desarrollo | Z24: =SUM(G:G) -> 2085 | AA24: =Z24/60 -> 34.75 | AB24: =SUM(P:P) -> 1040 | AC24: =AB24/60 -> 17.333333
B25: Requisitos | C25: Introducir datos de Planificación/Monitorización(esfuerzo real / semana) S3 | E25: 180 | J25: =IF(SUM(D25:I25)=0,"",SUM(D25:I25)) -> 180 | K25: =SUM($J$5:J25) -> 1735 | L25: 3 | N25: 120 | P25: 120 | S25: =SUM(M25:R25) -> 240 | T25: =SUM($S$5:S25) -> 1720 | U25: 5 | V25: Completada | Y25: Cambios | Z25: =SUM(H:H) -> 160 | AA25: =Z25/60 -> 2.6666667 | AB25: =SUM(Q:Q) -> 85 | AC25: =AB25/60 -> 1.4166667
B26: Requisitos | C26: Registrar datos de calidad S3 | E26: 10 | F26: 10 | G26: 10 | J26: =IF(SUM(D26:I26)=0,"",SUM(D26:I26)) -> 30 | K26: =SUM($J$5:J26) -> 1765 | L26: 3 | N26: 10 | O26: 10 | P26: 10 | S26: =SUM(M26:R26) -> 30 | T26: =SUM($S$5:S26) -> 1750 | U26: 5 | V26: Completada | Y26: Calidad | Z26: =SUM(I:I) -> 160 | AA26: =Z26/60 -> 2.6666667 | AB26: =SUM(R:R) -> 100 | AC26: =AB26/60 -> 1.6666667
Y28: Total | Z28: =SUM(Z21:Z26) -> 8170 | AA28: =SUM(AA21:AA26) -> 136.16667 | AB28: =SUM(AB21:AB26) -> 2995 | AC28: =SUM(AC21:AC26) -> 49.916667
J29: =IF(SUM(D29:I29)=0,"",SUM(D29:I29))
J30: =IF(SUM(D30:I30)=0,"",SUM(D30:I30))
B31: Estrategia | C31: Estimar Puntos de Función sobre las US | D31: 10 | E31: 10 | F31: 10 | G31: 10 | J31: =IF(SUM(D31:I31)=0,"",SUM(D31:I31)) -> 40 | K31: =SUM($J$5:J31) -> 1805 | L31: 4 | M31: 10 | N31: 10 | O31: 10 | P31: 10 | S31: =SUM(M31:R31) -> 40 | T31: =SUM($S$5:S31) -> 1790 | U31: 4 | V31: Completada
B32: Estrategia | C32: Calcular esfuerzo (horas) | E32: 15 | G32: 30 | J32: =IF(SUM(D32:I32)=0,"",SUM(D32:I32)) -> 45 | K32: =SUM($J$5:J32) -> 1850 | L32: 4 | N32: 35 | P32: 30 | S32: =SUM(M32:R32) -> 65 | T32: =SUM($S$5:S32) -> 1855 | U32: 5 | V32: Completada
B33: Estrategia | C33: Establecer estrategia de desarrollo (US Sprint 1 y Sprint 2) | D33: 10 | E33: 10 | F33: 10 | G33: 10 | J33: =IF(SUM(D33:I33)=0,"",SUM(D33:I33)) -> 40 | K33: =SUM($J$5:J33) -> 1890 | L33: 4 | M33: 10 | N33: 10 | O33: 10 | P33: 10 | S33: =SUM(M33:R33) -> 40 | T33: =SUM($S$5:S33) -> 1895 | U33: 4 | V33: Completada
B34: Estrategia | C34: Elaborar documento de Estrategia | D34: 180 | J34: =IF(SUM(D34:I34)=0,"",SUM(D34:I34)) -> 180 | K34: =SUM($J$5:J34) -> 2070 | L34: 4 | M34: 60 | N34: 30 | P34: 105 | S34: =SUM(M34:R34) -> 195 | T34: =SUM($S$5:S34) -> 2090 | U34: 5 | V34: Completada
B35: Estrategia | C35: Elaborar Sprint Backlog con Sprint Goal y tareas de calidad | D35: 10 | E35: 10 | F35: 10 | G35: 10 | J35: =IF(SUM(D35:I35)=0,"",SUM(D35:I35)) -> 40 | K35: =SUM($J$5:J35) -> 2110 | L35: 4 | M35: 15 | N35: 15 | O35: 15 | P35: 15 | S35: =SUM(M35:R35) -> 60 | T35: =SUM($S$5:S35) -> 2150 | U35: 4 | V35: Completada
B36: Estrategia | C36: Inspeccionar outputs de Estrategia (Q) | F36: 180 | J36: =IF(SUM(D36:I36)=0,"",SUM(D36:I36)) -> 180 | K36: =SUM($J$5:J36) -> 2290 | L36: 4 | O36: 120 | S36: =SUM(M36:R36) -> 120 | T36: =SUM($S$5:S36) -> 2270 | U36: 6 | V36: Completada
B37: Estrategia | C37: Poner en línea base Estrategia y Sprint Backlog (GCS) | D37: 10 | E37: 10 | F37: 10 | G37: 10 | J37: =IF(SUM(D37:I37)=0,"",SUM(D37:I37)) -> 40 | K37: =SUM($J$5:J37) -> 2330 | L37: 4 | M37: 15 | N37: 15 | O37: 15 | P37: 15 | S37: =SUM(M37:R37) -> 60 | T37: =SUM($S$5:S37) -> 2330 | U37: 5 | V37: Completada
B38: Estrategia | C38: Introducir datos de Planificación/Monitorización S4 (esfuerzo real / semana) | E38: 10 | F38: 10 | G38: 10 | J38: =IF(SUM(D38:I38)=0,"",SUM(D38:I38)) -> 30 | K38: =SUM($J$5:J38) -> 2360 | L38: 4 | N38: 10 | O38: 10 | P38: 10 | S38: =SUM(M38:R38) -> 30 | T38: =SUM($S$5:S38) -> 2360 | U38: 6 | V38: Completada
B39: Estrategia | C39: Registrar datos de calidad S4 | D39: 5 | E39: 5 | F39: 5 | G39: 5 | J39: =IF(SUM(D39:I39)=0,"",SUM(D39:I39)) -> 20 | K39: =SUM($J$5:J39) -> 2380 | L39: 4 | M39: 5 | N39: 5 | O39: 5 | P39: 5 | S39: =SUM(M39:R39) -> 20 | T39: =SUM($S$5:S39) -> 2380 | U39: 4 | V39: Completada
J41: =IF(SUM(D41:I41)=0,"",SUM(D41:I41))
J42: =IF(SUM(D42:I42)=0,"",SUM(D42:I42))
B43: Planificación | C43: Realizar Plan de Gestión de Configuración (PGCS) | D43: 10 | E43: 10 | F43: 10 | G43: 10 | J43: =IF(SUM(D43:I43)=0,"",SUM(D43:I43)) -> 40 | K43: =SUM($J$5:J43) -> 2420 | L43: 5 | M43: 5 | N43: 40 | O43: 5 | P43: 35 | S43: =SUM(M43:R43) -> 85 | T43: =SUM($S$5:S43) -> 2465 | U43: 5 | V43: Completada
B44: Planificación | C44: Realizar Plan de Calidad, DoD y matriz de evidencias | G44: 180 | J44: =IF(SUM(D44:I44)=0,"",SUM(D44:I44)) -> 180 | K44: =SUM($J$5:J44) -> 2600 | L44: 5 | P44: 180 | S44: =SUM(M44:R44) -> 180 | T44: =SUM($S$5:S44) -> 2645 | U44: 6 | V44: Completada
B45: Planificación | C45: Realizar Plan de Proyecto del Sprint 1 | E45: 10 | F45: 10 | G45: 10 | J45: =IF(SUM(D45:I45)=0,"",SUM(D45:I45)) -> 30 | K45: =SUM($J$5:J45) -> 2630 | L45: 5 | N45: 10 | O45: 10 | P45: 10 | S45: =SUM(M45:R45) -> 30 | T45: =SUM($S$5:S45) -> 2675 | U45: 6 | V45: Completada
B46: Planificación | C46: Realizar Diagrama de Gantt del Sprint 1 | D46: 10 | E46: 10 | F46: 10 | G46: 10 | J46: =IF(SUM(D46:I46)=0,"",SUM(D46:I46)) -> 40 | K46: =SUM($J$5:J46) -> 2670 | L46: 5 | M46: 10 | N46: 10 | O46: 10 | P46: 10 | S46: =SUM(M46:R46) -> 40 | T46: =SUM($S$5:S46) -> 2715 | U46: 5 | V46: Completada
B47: Planificación | C47: Inspeccionar planes (Q) y poner en línea base (GCS) | E47: 10 | F47: 10 | G47: 10 | J47: =IF(SUM(D47:I47)=0,"",SUM(D47:I47)) -> 30 | K47: =SUM($J$5:J47) -> 2700 | L47: 5 | S47: =SUM(M47:R47) -> 0 | T47: =SUM($S$5:S47) -> 2715 | V47: En curso
B48: Planificación | C48: Introducir datos de Planificación/Monitorización S5 (esfuerzo real / semana) | D48: 5 | E48: 5 | F48: 5 | G48: 5 | J48: =IF(SUM(D48:I48)=0,"",SUM(D48:I48)) -> 20 | K48: =SUM($J$5:J48) -> 2720 | L48: 5 | M48: 5 | N48: 5 | O48: 5 | P48: 5 | S48: =SUM(M48:R48) -> 20 | T48: =SUM($S$5:S48) -> 2735 | U48: 5 | V48: Completada
B49: Planificación | C49: Registrar datos de calidad S5: revisiones, pruebas y defectos | D49: =$Z$15 -> 30 | E49: =$Z$15 -> 30 | F49: =$Z$15 -> 30 | G49: =$Z$15 -> 30 | J49: =IF(SUM(D49:I49)=0,"",SUM(D49:I49)) -> 120 | K49: =SUM($J$5:J49) -> 2840 | L49: 5 | M49: 30 | N49: 20 | P49: 40 | S49: =SUM(M49:R49) -> 90 | T49: =SUM($S$5:S49) -> 2825 | U49: 5 | V49: Completada
J50: =IF(SUM(D50:I50)=0,"",SUM(D50:I50))
J51: =IF(SUM(D51:I51)=0,"",SUM(D51:I51))
B52: Diseño | C52: Realizar diagramas de Casos de Uso | D52: 10 | E52: 10 | F52: 10 | G52: 10 | J52: =IF(SUM(D52:I52)=0,"",SUM(D52:I52)) -> 40 | K52: =SUM($J$5:J52) -> 2880 | L52: 6 | M52: 5 | N52: 15 | O52: 5 | P52: 25 | S52: =SUM(M52:R52) -> 50 | T52: =SUM($S$5:S52) -> 2875 | U52: 5 | V52: Completada
B53: Diseño | C53: Realizar modelo Entidad/Relación y BBDD | G53: 120 | J53: =IF(SUM(D53:I53)=0,"",SUM(D53:I53)) -> 120 | K53: =SUM($J$5:J53) -> 3000 | L53: 6 | S53: =SUM(M53:R53) -> 0 | T53: =SUM($S$5:S53) -> 2875 | V53: En curso
B54: Diseño | C54: Diseñar pantallas | E54: 10 | F54: 10 | G54: 10 | J54: =IF(SUM(D54:I54)=0,"",SUM(D54:I54)) -> 30 | K54: =SUM($J$5:J54) -> 3030 | L54: 6 | S54: =SUM(M54:R54) -> 0 | T54: =SUM($S$5:S54) -> 2875 | V54: En curso
B55: Diseño | C55: Inspeccionar diseño (Q) y poner en línea base (GCS) | D55: 5 | E55: 5 | F55: 5 | G55: 5 | J55: =IF(SUM(D55:I55)=0,"",SUM(D55:I55)) -> 20 | K55: =SUM($J$5:J55) -> 3050 | L55: 6 | M55: 5 | N55: 5 | O55: 5 | P55: 5 | S55: =SUM(M55:R55) -> 20 | T55: =SUM($S$5:S55) -> 2895
B56: Diseño | C56: Introducir datos de Planificación/Monitorización S6 (esfuerzo real / semana, US) | D56: =$Z$15 -> 30 | E56: =$Z$15 -> 30 | F56: =$Z$15 -> 30 | G56: =$Z$15 -> 30 | J56: =IF(SUM(D56:I56)=0,"",SUM(D56:I56)) -> 120 | K56: =SUM($J$5:J56) -> 3170 | L56: 6 | M56: 10 | N56: 20 | O56: 60 | P56: 10 | S56: =SUM(M56:R56) -> 100 | T56: =SUM($S$5:S56) -> 2995
J57: =IF(SUM(D57:I57)=0,"",SUM(D57:I57))
J58: =IF(SUM(D58:I58)=0,"",SUM(D58:I58))
B59: Implementación | C59: Implementar BBDD | E59: 240 | G59: 240 | J59: =IF(SUM(D59:I59)=0,"",SUM(D59:I59)) -> 480 | K59: =SUM($J$5:J59) -> 3650 | L59: 7 | S59: =SUM(M59:R59) -> 0 | T59: =SUM($S$5:S59) -> 2995
B60: Implementación | C60: Implementar pantallas | D60: 180 | F60: 180 | J60: =IF(SUM(D60:I60)=0,"",SUM(D60:I60)) -> 360 | K60: =SUM($J$5:J60) -> 4010 | L60: 7 | S60: =SUM(M60:R60) -> 0 | T60: =SUM($S$5:S60) -> 2995
B61: Implementación | C61: Implementar US: Alta Vehículo | D61: 180 | F61: 180 | J61: =IF(SUM(D61:I61)=0,"",SUM(D61:I61)) -> 360 | K61: =SUM($J$5:J61) -> 4370 | L61: 7 | S61: =SUM(M61:R61) -> 0 | T61: =SUM($S$5:S61) -> 2995
B62: Implementación | C62: Implementar US: Marcas | E62: 120 | G62: 120 | J62: =IF(SUM(D62:I62)=0,"",SUM(D62:I62)) -> 240 | K62: =SUM($J$5:J62) -> 4610 | L62: 7 | S62: =SUM(M62:R62) -> 0 | T62: =SUM($S$5:S62) -> 2995
B63: Implementación | C63: Implementar US: Almacén | E63: 120 | G63: 120 | J63: =IF(SUM(D63:I63)=0,"",SUM(D63:I63)) -> 240 | K63: =SUM($J$5:J63) -> 4850 | L63: 7 | S63: =SUM(M63:R63) -> 0 | T63: =SUM($S$5:S63) -> 2995
B64: Implementación | C64: Implementar US: Desplegables (Gamma, Marchas, Techos, Puertas) | D64: 120 | F64: 120 | J64: =IF(SUM(D64:I64)=0,"",SUM(D64:I64)) -> 240 | K64: =SUM($J$5:J64) -> 5090 | L64: 7 | S64: =SUM(M64:R64) -> 0 | T64: =SUM($S$5:S64) -> 2995
B65: Implementación | C65: Implementar US: Listar coches (filtrado) | D65: 120 | F65: 120 | J65: =IF(SUM(D65:I65)=0,"",SUM(D65:I65)) -> 240 | K65: =SUM($J$5:J65) -> 5330 | L65: 7 | S65: =SUM(M65:R65) -> 0 | T65: =SUM($S$5:S65) -> 2995
B66: Implementación | C66: Integrar historias de usuario del sprint | E66: 120 | G66: 120 | J66: =IF(SUM(D66:I66)=0,"",SUM(D66:I66)) -> 240 | K66: =SUM($J$5:J66) -> 5570 | L66: 7 | S66: =SUM(M66:R66) -> 0 | T66: =SUM($S$5:S66) -> 2995
B67: Implementación | C67: Inspeccionar código (Q) y poner en línea base (GCS) | D67: 120 | E67: 120 | F67: 120 | G67: 120 | J67: =IF(SUM(D67:I67)=0,"",SUM(D67:I67)) -> 480 | K67: =SUM($J$5:J67) -> 6050 | L67: 7 | S67: =SUM(M67:R67) -> 0 | T67: =SUM($S$5:S67) -> 2995
B68: Implementación | C68: Introducir datos de Planificación/Monitorización S7 (esfuerzo real / semana, US implementadas) | D68: 120 | E68: 120 | F68: 120 | G68: 120 | J68: =IF(SUM(D68:I68)=0,"",SUM(D68:I68)) -> 480 | K68: =SUM($J$5:J68) -> 6530 | L68: 7 | S68: =SUM(M68:R68) -> 0 | T68: =SUM($S$5:S68) -> 2995
B69: Implementación | C69: Registrar datos de calidad S7: ejecucion, defectos y verificacion DoD | D69: 5 | E69: 5 | F69: 5 | G69: 5 | J69: =IF(SUM(D69:I69)=0,"",SUM(D69:I69)) -> 20 | K69: =SUM($J$5:J69) -> 6550 | L69: 7 | S69: =SUM(M69:R69) -> 0 | T69: =SUM($S$5:S69) -> 2995
J70: =IF(SUM(D70:I70)=0,"",SUM(D70:I70))
J71: =IF(SUM(D71:I71)=0,"",SUM(D71:I71))
B72: Pruebas | C72: Definir casos de prueba unitarios y de aceptación por US | D72: 120 | E72: 120 | F72: 120 | G72: 120 | J72: =IF(SUM(D72:I72)=0,"",SUM(D72:I72)) -> 480 | K72: =SUM($J$5:J72) -> 7030 | L72: 8 | S72: =SUM(M72:R72) -> 0 | T72: =SUM($S$5:S72) -> 2995
B73: Pruebas | C73: Ejecutar pruebas y registrar resultado esperado vs real y version | D73: 120 | E73: 120 | F73: 120 | G73: 120 | J73: =IF(SUM(D73:I73)=0,"",SUM(D73:I73)) -> 480 | K73: =SUM($J$5:J73) -> 7510 | L73: 8 | S73: =SUM(M73:R73) -> 0 | T73: =SUM($S$5:S73) -> 2995
B74: Pruebas | C74: Inspeccionar registros de pruebas, enlazar evidencias y poner en linea base (Q/GCS) | D74: 5 | E74: 5 | F74: 5 | G74: 5 | J74: =IF(SUM(D74:I74)=0,"",SUM(D74:I74)) -> 20 | K74: =SUM($J$5:J74) -> 7530 | L74: 8 | S74: =SUM(M74:R74) -> 0 | T74: =SUM($S$5:S74) -> 2995
B75: Pruebas | C75: Introducir datos de Planificación/Monitorización S8 (esfuerzo real / semana, US) | D75: =$Z$15 -> 30 | E75: =$Z$15 -> 30 | F75: =$Z$15 -> 30 | G75: =$Z$15 -> 30 | J75: =IF(SUM(D75:I75)=0,"",SUM(D75:I75)) -> 120 | K75: =SUM($J$5:J75) -> 7650 | L75: 8 | S75: =SUM(M75:R75) -> 0 | T75: =SUM($S$5:S75) -> 2995
J76: =IF(SUM(D76:I76)=0,"",SUM(D76:I76))
J77: =IF(SUM(D77:I77)=0,"",SUM(D77:I77))
B78: Retrospectiva | C78: Realizar informe de retrospectiva del Sprint 1 | D78: 180 | J78: =IF(SUM(D78:I78)=0,"",SUM(D78:I78)) -> 180 | K78: =SUM($J$5:J78) -> 7830 | L78: 9 | S78: =SUM(M78:R78) -> 0 | T78: =SUM($S$5:S78) -> 2995
B79: Retrospectiva | C79: Evaluar roles y equipo del Sprint 1 | D79: 15 | E79: 15 | F79: 15 | G79: 15 | J79: =IF(SUM(D79:I79)=0,"",SUM(D79:I79)) -> 60 | K79: =SUM($J$5:J79) -> 7890 | L79: 9 | S79: =SUM(M79:R79) -> 0 | T79: =SUM($S$5:S79) -> 2995
B80: Retrospectiva | C80: Revisar productos y procesos; dificultades, PF y PD | D80: 15 | E80: 15 | F80: 15 | G80: 15 | J80: =IF(SUM(D80:I80)=0,"",SUM(D80:I80)) -> 60 | K80: =SUM($J$5:J80) -> 7950 | L80: 9 | S80: =SUM(M80:R80) -> 0 | T80: =SUM($S$5:S80) -> 2995
B81: Retrospectiva | C81: Retrospectiva STARFISH (Keep / More / Start / Stop / Less) | D81: 20 | E81: 20 | F81: 20 | G81: 20 | J81: =IF(SUM(D81:I81)=0,"",SUM(D81:I81)) -> 80 | K81: =SUM($J$5:J81) -> 8030 | L81: 9 | S81: =SUM(M81:R81) -> 0 | T81: =SUM($S$5:S81) -> 2995
B82: Retrospectiva | C82: Introducir datos de Planificación/Monitorización S9 | D82: 5 | E82: 5 | F82: 5 | G82: 5 | J82: =IF(SUM(D82:I82)=0,"",SUM(D82:I82)) -> 20 | K82: =SUM($J$5:J82) -> 8050 | L82: 9 | S82: =SUM(M82:R82) -> 0 | T82: =SUM($S$5:S82) -> 2995
B83: Retrospectiva | C83: Lecciones aprendidas y mejoras al proceso | D83: =$Z$15 -> 30 | E83: =$Z$15 -> 30 | F83: =$Z$15 -> 30 | G83: =$Z$15 -> 30 | J83: =IF(SUM(D83:I83)=0,"",SUM(D83:I83)) -> 120 | K83: =SUM($J$5:J83) -> 8170 | L83: 9 | S83: =SUM(M83:R83) -> 0 | T83: =SUM($S$5:S83) -> 2995
J84: =IF(SUM(D84:I84)=0,"",SUM(D84:I84))
J85: =IF(SUM(D85:I85)=0,"",SUM(D85:I85))
J86: =IF(SUM(D86:I86)=0,"",SUM(D86:I86))
J87: =IF(SUM(D87:I87)=0,"",SUM(D87:I87))
J88: =IF(SUM(D88:I88)=0,"",SUM(D88:I88))
J89: =IF(SUM(D89:I89)=0,"",SUM(D89:I89))
J90: =IF(SUM(D90:I90)=0,"",SUM(D90:I90))
J91: =IF(SUM(D91:I91)=0,"",SUM(D91:I91))
J92: =IF(SUM(D92:I92)=0,"",SUM(D92:I92))
J93: =IF(SUM(D93:I93)=0,"",SUM(D93:I93))
J94: =IF(SUM(D94:I94)=0,"",SUM(D94:I94))
J95: =IF(SUM(D95:I95)=0,"",SUM(D95:I95))

Sheet Lider SM
C2: Lista de tareas de Líder / Scrum Master | G2: IMPORTANTE
D3: Total min. reales | E3: =SUM(E6:E88) -> 590 | G3: ¡ NO EDITAR ESTA PÁGINA ! Se genera automaticamente
C5: Fase | D5: Actividad | E5: Esfuerzo (minutos reales)
C6: =IF(ISBLANK(Plan!B5),"",Plan!B5) -> Lanzamiento | D6: =IF(ISBLANK(Plan!C5),"",Plan!C5) -> Asignar equipos y roles | E6: =IF(ISBLANK(Plan!B5),"",IF(Plan!M5>0,Plan!M5,"")) -> 10
C7: =IF(ISBLANK(Plan!B6),"",Plan!B6) -> Lanzamiento | D7: =IF(ISBLANK(Plan!C6),"",Plan!C6) -> Definir proceso de reuniones | E7: =IF(ISBLANK(Plan!B6),"",IF(Plan!M6>0,Plan!M6,"")) -> 20
C8: =IF(ISBLANK(Plan!B7),"",Plan!B7) -> Lanzamiento | D8: =IF(ISBLANK(Plan!C7),"",Plan!C7) -> Realizar Estándar de Documentación | E8: =IF(ISBLANK(Plan!B7),"",IF(Plan!M7>0,Plan!M7,""))
C9: =IF(ISBLANK(Plan!B8),"",Plan!B8) -> Lanzamiento | D9: =IF(ISBLANK(Plan!C8),"",Plan!C8) -> Realizar Estándar de Agendas | E9: =IF(ISBLANK(Plan!B8),"",IF(Plan!M8>0,Plan!M8,"")) -> 20
C10: =IF(ISBLANK(Plan!B9),"",Plan!B9) -> Lanzamiento | D10: =IF(ISBLANK(Plan!C9),"",Plan!C9) -> Realizar Estándar de Actas | E10: =IF(ISBLANK(Plan!B9),"",IF(Plan!M9>0,Plan!M9,"")) -> 20
C11: =IF(ISBLANK(Plan!B10),"",Plan!B10) -> Lanzamiento | D11: =IF(ISBLANK(Plan!C10),"",Plan!C10) -> Definir Ciclo de Vida a aplicar (actividades) | E11: =IF(ISBLANK(Plan!B10),"",IF(Plan!M10>0,Plan!M10,"")) -> 15
C12: =IF(ISBLANK(Plan!B11),"",Plan!B11) -> Lanzamiento | D12: =IF(ISBLANK(Plan!C11),"",Plan!C11) -> Definir outputs y plantillas del CV | E12: =IF(ISBLANK(Plan!B11),"",IF(Plan!M11>0,Plan!M11,"")) -> 20
C13: =IF(ISBLANK(Plan!B12),"",Plan!B12) -> Lanzamiento | D13: =IF(ISBLANK(Plan!C12),"",Plan!C12) -> Definir Entorno de Desarrollo | E13: =IF(ISBLANK(Plan!B12),"",IF(Plan!M12>0,Plan!M12,"")) -> 20
C14: =IF(ISBLANK(Plan!B13),"",Plan!B13) -> Lanzamiento | D14: =IF(ISBLANK(Plan!C13),"",Plan!C13) -> Configurar Entorno de Desarrollo | E14: =IF(ISBLANK(Plan!B13),"",IF(Plan!M13>0,Plan!M13,"")) -> 150
C15: =IF(ISBLANK(Plan!B14),"",Plan!B14) -> Lanzamiento | D15: =IF(ISBLANK(Plan!C14),"",Plan!C14) -> Definir Estándar de Codificación | E15: =IF(ISBLANK(Plan!B14),"",IF(Plan!M14>0,Plan!M14,"")) -> 15
E16: =IF(ISBLANK(Plan!B15),"",IF(Plan!M15>0,Plan!M15,"")) -> 5
E17: =IF(ISBLANK(Plan!B16),"",IF(Plan!M16>0,Plan!M16,""))
C18: =IF(ISBLANK(Plan!B15),"",Plan!B15) -> Lanzamiento | D18: =IF(ISBLANK(Plan!C15),"",Plan!C15) -> Introducir datos de Planificación/Monitorización S1 (esfuerzo real / semana) | E18: =IF(ISBLANK(Plan!B17),"",IF(Plan!M17>0,Plan!M17,""))
C19: =IF(ISBLANK(Plan!B16),"",Plan!B16) | D19: =IF(ISBLANK(Plan!C16),"",Plan!C16) | E19: =IF(ISBLANK(Plan!B18),"",IF(Plan!M18>0,Plan!M18,""))
C20: =IF(ISBLANK(Plan!B17),"",Plan!B17) | D20: =IF(ISBLANK(Plan!C17),"",Plan!C17) | E20: =IF(ISBLANK(Plan!B19),"",IF(Plan!M19>0,Plan!M19,"")) -> 30
C21: =IF(ISBLANK(Plan!B18),"",Plan!B18) | D21: =IF(ISBLANK(Plan!C18),"",Plan!C18) | E21: =IF(ISBLANK(Plan!B20),"",IF(Plan!M20>0,Plan!M20,"")) -> 5
C22: =IF(ISBLANK(Plan!B19),"",Plan!B19) -> Requisitos | D22: =IF(ISBLANK(Plan!C19),"",Plan!C19) -> Obtener Historias de Usuario (US) | E22: =IF(ISBLANK(Plan!B21),"",IF(Plan!M21>0,Plan!M21,""))
C23: =IF(ISBLANK(Plan!B20),"",Plan!B20) -> Requisitos | D23: =IF(ISBLANK(Plan!C20),"",Plan!C20) -> Describir las US según plantilla (Como/Quiero/Para + criterios de aceptación) | E23: =IF(ISBLANK(Plan!B22),"",IF(Plan!M22>0,Plan!M22,"")) -> 10
C24: =IF(ISBLANK(Plan!B21),"",Plan!B21) -> Requisitos | D24: =IF(ISBLANK(Plan!C21),"",Plan!C21) -> Completar campos de US para puntos de función | E24: =IF(ISBLANK(Plan!B23),"",IF(Plan!M23>0,Plan!M23,"")) -> 60
C25: =IF(ISBLANK(Plan!B22),"",Plan!B22) -> Requisitos | D25: =IF(ISBLANK(Plan!C22),"",Plan!C22) -> Elaborar Product Backlog priorizado | E25: =IF(ISBLANK(Plan!B24),"",IF(Plan!M24>0,Plan!M24,"")) -> 5
C26: =IF(ISBLANK(Plan!B23),"",Plan!B23) -> Requisitos | D26: =IF(ISBLANK(Plan!C23),"",Plan!C23) -> Inspeccionar las US y criterios de aceptacion (Q) | E26: =IF(ISBLANK(Plan!B25),"",IF(Plan!M25>0,Plan!M25,""))
C27: =IF(ISBLANK(Plan!B24),"",Plan!B24) -> Requisitos | D27: =IF(ISBLANK(Plan!C24),"",Plan!C24) -> Poner en línea base las US (GCS) | E27: =IF(ISBLANK(Plan!B26),"",IF(Plan!M26>0,Plan!M26,""))
C28: =IF(ISBLANK(Plan!B25),"",Plan!B25) -> Requisitos | D28: =IF(ISBLANK(Plan!C25),"",Plan!C25) -> Introducir datos de Planificación/Monitorización(esfuerzo real / semana) S3 | E28: =IF(ISBLANK(Plan!B27),"",IF(Plan!M27>0,Plan!M27,""))
C29: =IF(ISBLANK(Plan!B26),"",Plan!B26) -> Requisitos | D29: =IF(ISBLANK(Plan!C26),"",Plan!C26) -> Registrar datos de calidad S3 | E29: =IF(ISBLANK(Plan!B28),"",IF(Plan!M28>0,Plan!M28,""))
... C49: =IF(ISBLANK(Plan!B46),"",Plan!B46) -> Planificación | D49: =IF(ISBLANK(Plan!C46),"",Plan!C46) -> Realizar Diagrama de Gantt del Sprint 1 | E49: =IF(ISBLANK(Plan!B48),"",IF(Plan!M48>0,Plan!M48,"")) -> 5
C50: =IF(ISBLANK(Plan!#REF!),"",Plan!#REF!) -> #REF! | D50: =IF(ISBLANK(Plan!#REF!),"",Plan!#REF!) -> #REF! | E50: =IF(ISBLANK(Plan!B49),"",IF(Plan!M49>0,Plan!M49,"")) -> 30
C51: =IF(ISBLANK(Plan!B47),"",Plan!B47) -> Planificación | D51: =IF(ISBLANK(Plan!C47),"",Plan!C47) -> Inspeccionar planes (Q) y poner en línea base (GCS) | E51: =IF(ISBLANK(Plan!B50),"",IF(Plan!M50>0,Plan!M50,""))
C52: =IF(ISBLANK(Plan!B48),"",Plan!B48) -> Planificación | D52: =IF(ISBLANK(Plan!C48),"",Plan!C48) -> Introducir datos de Planificación/Monitorización S5 (esfuerzo real / semana) | E52: =IF(ISBLANK(Plan!B51),"",IF(Plan!M51>0,Plan!M51,""))
C53: =IF(ISBLANK(Plan!B49),"",Plan!B49) -> Planificación | D53: =IF(ISBLANK(Plan!C49),"",Plan!C49) -> Registrar datos de calidad S5: revisiones, pruebas y defectos | E53: =IF(ISBLANK(Plan!B52),"",IF(Plan!M52>0,Plan!M52,"")) -> 5
C54: =IF(ISBLANK(Plan!B50),"",Plan!B50) | D54: =IF(ISBLANK(Plan!C50),"",Plan!C50) | E54: =IF(ISBLANK(Plan!B53),"",IF(Plan!M53>0,Plan!M53,""))
C55: =IF(ISBLANK(Plan!B51),"",Plan!B51) | D55: =IF(ISBLANK(Plan!C51),"",Plan!C51) | E55: =IF(ISBLANK(Plan!B54),"",IF(Plan!M54>0,Plan!M54,""))
C56: =IF(ISBLANK(Plan!B52),"",Plan!B52) -> Diseño | D56: =IF(ISBLANK(Plan!C52),"",Plan!C52) -> Realizar diagramas de Casos de Uso | E56: =IF(ISBLANK(Plan!B55),"",IF(Plan!M55>0,Plan!M55,"")) -> 5
C57: =IF(ISBLANK(Plan!B53),"",Plan!B53) -> Diseño | D57: =IF(ISBLANK(Plan!C53),"",Plan!C53) -> Realizar modelo Entidad/Relación y BBDD | E57: =IF(ISBLANK(Plan!B56),"",IF(Plan!M56>0,Plan!M56,"")) -> 10
C58: =IF(ISBLANK(Plan!B54),"",Plan!B54) -> Diseño | D58: =IF(ISBLANK(Plan!C54),"",Plan!C54) -> Diseñar pantallas | E58: =IF(ISBLANK(Plan!B57),"",IF(Plan!M57>0,Plan!M57,""))
C59: =IF(ISBLANK(Plan!B55),"",Plan!B55) -> Diseño | D59: =IF(ISBLANK(Plan!C55),"",Plan!C55) -> Inspeccionar diseño (Q) y poner en línea base (GCS) | E59: =IF(ISBLANK(Plan!B58),"",IF(Plan!M58>0,Plan!M58,""))
C60: =IF(ISBLANK(Plan!B56),"",Plan!B56) -> Diseño | D60: =IF(ISBLANK(Plan!C56),"",Plan!C56) -> Introducir datos de Planificación/Monitorización S6 (esfuerzo real / semana, US) | E60: =IF(ISBLANK(Plan!B59),"",IF(Plan!M59>0,Plan!M59,""))
C61: =IF(ISBLANK(Plan!B57),"",Plan!B57) | D61: =IF(ISBLANK(Plan!C57),"",Plan!C57) | E61: =IF(ISBLANK(Plan!B60),"",IF(Plan!M60>0,Plan!M60,""))
C62: =IF(ISBLANK(Plan!B58),"",Plan!B58) | D62: =IF(ISBLANK(Plan!C58),"",Plan!C58) | E62: =IF(ISBLANK(Plan!B61),"",IF(Plan!M61>0,Plan!M61,""))
... C73: =IF(ISBLANK(Plan!B69),"",Plan!B69) -> Implementación | D73: =IF(ISBLANK(Plan!C69),"",Plan!C69) -> Registrar datos de calidad S7: ejecucion, defectos y verificacion DoD | E73: =IF(ISBLANK(Plan!B72),"",IF(Plan!M72>0,Plan!M72,""))
C74: =IF(ISBLANK(Plan!#REF!),"",Plan!#REF!) -> #REF! | D74: =IF(ISBLANK(Plan!#REF!),"",Plan!#REF!) -> #REF! | E74: =IF(ISBLANK(Plan!B73),"",IF(Plan!M73>0,Plan!M73,""))
C75: =IF(ISBLANK(Plan!B70),"",Plan!B70) | D75: =IF(ISBLANK(Plan!C70),"",Plan!C70) | E75: =IF(ISBLANK(Plan!B74),"",IF(Plan!M74>0,Plan!M74,""))
C76: =IF(ISBLANK(Plan!B71),"",Plan!B71) | D76: =IF(ISBLANK(Plan!C71),"",Plan!C71) | E76: =IF(ISBLANK(Plan!B75),"",IF(Plan!M75>0,Plan!M75,""))
C77: =IF(ISBLANK(Plan!B72),"",Plan!B72) -> Pruebas | D77: =IF(ISBLANK(Plan!C72),"",Plan!C72) -> Definir casos de prueba unitarios y de aceptación por US | E77: =IF(ISBLANK(Plan!B76),"",IF(Plan!M76>0,Plan!M76,""))
C78: =IF(ISBLANK(Plan!B73),"",Plan!B73) -> Pruebas | D78: =IF(ISBLANK(Plan!C73),"",Plan!C73) -> Ejecutar pruebas y registrar resultado esperado vs real y version | E78: =IF(ISBLANK(Plan!B77),"",IF(Plan!M77>0,Plan!M77,""))
C79: =IF(ISBLANK(Plan!B74),"",Plan!B74) -> Pruebas | D79: =IF(ISBLANK(Plan!C74),"",Plan!C74) -> Inspeccionar registros de pruebas, enlazar evidencias y poner en linea base (Q/GCS) | E79: =IF(ISBLANK(Plan!B78),"",IF(Plan!M78>0,Plan!M78,""))
C80: =IF(ISBLANK(Plan!B75),"",Plan!B75) -> Pruebas | D80: =IF(ISBLANK(Plan!C75),"",Plan!C75) -> Introducir datos de Planificación/Monitorización S8 (esfuerzo real / semana, US) | E80: =IF(ISBLANK(Plan!B79),"",IF(Plan!M79>0,Plan!M79,""))
C81: =IF(ISBLANK(Plan!B76),"",Plan!B76) | D81: =IF(ISBLANK(Plan!C76),"",Plan!C76) | E81: =IF(ISBLANK(Plan!B80),"",IF(Plan!M80>0,Plan!M80,""))
C82: =IF(ISBLANK(Plan!B77),"",Plan!B77) | D82: =IF(ISBLANK(Plan!C77),"",Plan!C77) | E82: =IF(ISBLANK(Plan!B81),"",IF(Plan!M81>0,Plan!M81,""))
C83: =IF(ISBLANK(Plan!B78),"",Plan!B78) -> Retrospectiva | D83: =IF(ISBLANK(Plan!C78),"",Plan!C78) -> Realizar informe de retrospectiva del Sprint 1 | E83: =IF(ISBLANK(Plan!B82),"",IF(Plan!M82>0,Plan!M82,""))
C84: =IF(ISBLANK(Plan!B79),"",Plan!B79) -> Retrospectiva | D84: =IF(ISBLANK(Plan!C79),"",Plan!C79) -> Evaluar roles y equipo del Sprint 1 | E84: =IF(ISBLANK(Plan!B83),"",IF(Plan!M83>0,Plan!M83,""))
C85: =IF(ISBLANK(Plan!B80),"",Plan!B80) -> Retrospectiva | D85: =IF(ISBLANK(Plan!C80),"",Plan!C80) -> Revisar productos y procesos; dificultades, PF y PD | E85: =IF(ISBLANK(Plan!B84),"",IF(Plan!M84>0,Plan!M84,""))
C86: =IF(ISBLANK(Plan!B81),"",Plan!B81) -> Retrospectiva | D86: =IF(ISBLANK(Plan!C81),"",Plan!C81) -> Retrospectiva STARFISH (Keep / More / Start / Stop / Less) | E86: =IF(ISBLANK(Plan!B85),"",IF(Plan!M85>0,Plan!M85,""))
... C88: =IF(ISBLANK(Plan!B83),"",Plan!B83) -> Retrospectiva | D88: =IF(ISBLANK(Plan!C83),"",Plan!C83) -> Lecciones aprendidas y mejoras al proceso | E88: =IF(ISBLANK(Plan!B87),"",IF(Plan!M87>0,Plan!M87,""))
D89: =IF(ISBLANK(Plan!C84),"",Plan!C84)
D92: =IF(ISBLANK(Plan!C87),"",Plan!C87)
D93: =IF(ISBLANK(Plan!C88),"",Plan!C88)
D94: =IF(ISBLANK(Plan!C89),"",Plan!C89)
D95: =IF(ISBLANK(Plan!C90),"",Plan!C90)
D96: =IF(ISBLANK(Plan!C91),"",Plan!C91)
D97: =IF(ISBLANK(Plan!C92),"",Plan!C92)
D98: =IF(ISBLANK(Plan!C93),"",Plan!C93)
D99: =IF(ISBLANK(Plan!C94),"",Plan!C94)
D100: =IF(ISBLANK(Plan!C95),"",Plan!C95)

Sheet Producto Owner
C2: Lista de tareas de Product Owner | G2: IMPORTANTE
D3: Total min. reales | E3: =SUM(E6:E88) -> 675 | G3: ¡ NO EDITAR ESTA PÁGINA ! Se genera automaticamente
C5: Fase | D5: Actividad | E5: Esfuerzo (minutos reales)
C6: =IF(ISBLANK(Plan!B5),"",Plan!B5) -> Lanzamiento | D6: =IF(ISBLANK(Plan!C5),"",Plan!C5) -> Asignar equipos y roles | E6: =IF(ISBLANK(Plan!B5),"",IF(Plan!N5>0,Plan!N5,"")) -> 10
C7: =IF(ISBLANK(Plan!B6),"",Plan!B6) -> Lanzamiento | D7: =IF(ISBLANK(Plan!C6),"",Plan!C6) -> Definir proceso de reuniones | E7: =IF(ISBLANK(Plan!B6),"",IF(Plan!N6>0,Plan!N6,"")) -> 20
C8: =IF(ISBLANK(Plan!B7),"",Plan!B7) -> Lanzamiento | D8: =IF(ISBLANK(Plan!C7),"",Plan!C7) -> Realizar Estándar de Documentación | E8: =IF(ISBLANK(Plan!B7),"",IF(Plan!N7>0,Plan!N7,"")) -> 30
C9: =IF(ISBLANK(Plan!B8),"",Plan!B8) -> Lanzamiento | D9: =IF(ISBLANK(Plan!C8),"",Plan!C8) -> Realizar Estándar de Agendas | E9: =IF(ISBLANK(Plan!B8),"",IF(Plan!N8>0,Plan!N8,"")) -> 20
C10: =IF(ISBLANK(Plan!B9),"",Plan!B9) -> Lanzamiento | D10: =IF(ISBLANK(Plan!C9),"",Plan!C9) -> Realizar Estándar de Actas | E10: =IF(ISBLANK(Plan!B9),"",IF(Plan!N9>0,Plan!N9,""))
C11: =IF(ISBLANK(Plan!B10),"",Plan!B10) -> Lanzamiento | D11: =IF(ISBLANK(Plan!C10),"",Plan!C10) -> Definir Ciclo de Vida a aplicar (actividades) | E11: =IF(ISBLANK(Plan!B10),"",IF(Plan!N10>0,Plan!N10,"")) -> 15
C12: =IF(ISBLANK(Plan!B11),"",Plan!B11) -> Lanzamiento | D12: =IF(ISBLANK(Plan!C11),"",Plan!C11) -> Definir outputs y plantillas del CV | E12: =IF(ISBLANK(Plan!B11),"",IF(Plan!N11>0,Plan!N11,""))
C13: =IF(ISBLANK(Plan!B12),"",Plan!B12) -> Lanzamiento | D13: =IF(ISBLANK(Plan!C12),"",Plan!C12) -> Definir Entorno de Desarrollo | E13: =IF(ISBLANK(Plan!B12),"",IF(Plan!N12>0,Plan!N12,"")) -> 20
C14: =IF(ISBLANK(Plan!B13),"",Plan!B13) -> Lanzamiento | D14: =IF(ISBLANK(Plan!C13),"",Plan!C13) -> Configurar Entorno de Desarrollo | E14: =IF(ISBLANK(Plan!B13),"",IF(Plan!N13>0,Plan!N13,""))
C15: =IF(ISBLANK(Plan!B14),"",Plan!B14) -> Lanzamiento | D15: =IF(ISBLANK(Plan!C14),"",Plan!C14) -> Definir Estándar de Codificación | E15: =IF(ISBLANK(Plan!B14),"",IF(Plan!N14>0,Plan!N14,"")) -> 15
E16: =IF(ISBLANK(Plan!B15),"",IF(Plan!N15>0,Plan!N15,"")) -> 5
E17: =IF(ISBLANK(Plan!B16),"",IF(Plan!N16>0,Plan!N16,""))
C18: =IF(ISBLANK(Plan!B15),"",Plan!B15) -> Lanzamiento | D18: =IF(ISBLANK(Plan!C15),"",Plan!C15) -> Introducir datos de Planificación/Monitorización S1 (esfuerzo real / semana) | E18: =IF(ISBLANK(Plan!B17),"",IF(Plan!N17>0,Plan!N17,""))
C19: =IF(ISBLANK(Plan!B16),"",Plan!B16) | D19: =IF(ISBLANK(Plan!C16),"",Plan!C16) | E19: =IF(ISBLANK(Plan!B18),"",IF(Plan!N18>0,Plan!N18,""))
C20: =IF(ISBLANK(Plan!B17),"",Plan!B17) | D20: =IF(ISBLANK(Plan!C17),"",Plan!C17) | E20: =IF(ISBLANK(Plan!B19),"",IF(Plan!N19>0,Plan!N19,"")) -> 30
C21: =IF(ISBLANK(Plan!B18),"",Plan!B18) | D21: =IF(ISBLANK(Plan!C18),"",Plan!C18) | E21: =IF(ISBLANK(Plan!B20),"",IF(Plan!N20>0,Plan!N20,"")) -> 5
C22: =IF(ISBLANK(Plan!B19),"",Plan!B19) -> Requisitos | D22: =IF(ISBLANK(Plan!C19),"",Plan!C19) -> Obtener Historias de Usuario (US) | E22: =IF(ISBLANK(Plan!B21),"",IF(Plan!N21>0,Plan!N21,"")) -> 45
C23: =IF(ISBLANK(Plan!B20),"",Plan!B20) -> Requisitos | D23: =IF(ISBLANK(Plan!C20),"",Plan!C20) -> Describir las US según plantilla (Como/Quiero/Para + criterios de aceptación) | E23: =IF(ISBLANK(Plan!B22),"",IF(Plan!N22>0,Plan!N22,"")) -> 10
C24: =IF(ISBLANK(Plan!B21),"",Plan!B21) -> Requisitos | D24: =IF(ISBLANK(Plan!C21),"",Plan!C21) -> Completar campos de US para puntos de función | E24: =IF(ISBLANK(Plan!B23),"",IF(Plan!N23>0,Plan!N23,"")) -> 60
C25: =IF(ISBLANK(Plan!B22),"",Plan!B22) -> Requisitos | D25: =IF(ISBLANK(Plan!C22),"",Plan!C22) -> Elaborar Product Backlog priorizado | E25: =IF(ISBLANK(Plan!B24),"",IF(Plan!N24>0,Plan!N24,"")) -> 5
C26: =IF(ISBLANK(Plan!B23),"",Plan!B23) -> Requisitos | D26: =IF(ISBLANK(Plan!C23),"",Plan!C23) -> Inspeccionar las US y criterios de aceptacion (Q) | E26: =IF(ISBLANK(Plan!B25),"",IF(Plan!N25>0,Plan!N25,"")) -> 120
C27: =IF(ISBLANK(Plan!B24),"",Plan!B24) -> Requisitos | D27: =IF(ISBLANK(Plan!C24),"",Plan!C24) -> Poner en línea base las US (GCS) | E27: =IF(ISBLANK(Plan!B26),"",IF(Plan!N26>0,Plan!N26,"")) -> 10
C28: =IF(ISBLANK(Plan!B25),"",Plan!B25) -> Requisitos | D28: =IF(ISBLANK(Plan!C25),"",Plan!C25) -> Introducir datos de Planificación/Monitorización(esfuerzo real / semana) S3 | E28: =IF(ISBLANK(Plan!B27),"",IF(Plan!N27>0,Plan!N27,""))
C29: =IF(ISBLANK(Plan!B26),"",Plan!B26) -> Requisitos | D29: =IF(ISBLANK(Plan!C26),"",Plan!C26) -> Registrar datos de calidad S3 | E29: =IF(ISBLANK(Plan!B28),"",IF(Plan!N28>0,Plan!N28,""))
... C49: =IF(ISBLANK(Plan!B46),"",Plan!B46) -> Planificación | D49: =IF(ISBLANK(Plan!C46),"",Plan!C46) -> Realizar Diagrama de Gantt del Sprint 1 | E49: =IF(ISBLANK(Plan!B48),"",IF(Plan!N48>0,Plan!N48,"")) -> 5
C50: =IF(ISBLANK(Plan!#REF!),"",Plan!#REF!) -> #REF! | D50: =IF(ISBLANK(Plan!#REF!),"",Plan!#REF!) -> #REF! | E50: =IF(ISBLANK(Plan!B49),"",IF(Plan!N49>0,Plan!N49,"")) -> 20
C51: =IF(ISBLANK(Plan!B47),"",Plan!B47) -> Planificación | D51: =IF(ISBLANK(Plan!C47),"",Plan!C47) -> Inspeccionar planes (Q) y poner en línea base (GCS) | E51: =IF(ISBLANK(Plan!B50),"",IF(Plan!N50>0,Plan!N50,""))
C52: =IF(ISBLANK(Plan!B48),"",Plan!B48) -> Planificación | D52: =IF(ISBLANK(Plan!C48),"",Plan!C48) -> Introducir datos de Planificación/Monitorización S5 (esfuerzo real / semana) | E52: =IF(ISBLANK(Plan!B51),"",IF(Plan!N51>0,Plan!N51,""))
C53: =IF(ISBLANK(Plan!B49),"",Plan!B49) -> Planificación | D53: =IF(ISBLANK(Plan!C49),"",Plan!C49) -> Registrar datos de calidad S5: revisiones, pruebas y defectos | E53: =IF(ISBLANK(Plan!B52),"",IF(Plan!N52>0,Plan!N52,"")) -> 15
C54: =IF(ISBLANK(Plan!B50),"",Plan!B50) | D54: =IF(ISBLANK(Plan!C50),"",Plan!C50) | E54: =IF(ISBLANK(Plan!B53),"",IF(Plan!N53>0,Plan!N53,""))
C55: =IF(ISBLANK(Plan!B51),"",Plan!B51) | D55: =IF(ISBLANK(Plan!C51),"",Plan!C51) | E55: =IF(ISBLANK(Plan!B54),"",IF(Plan!N54>0,Plan!N54,""))
C56: =IF(ISBLANK(Plan!B52),"",Plan!B52) -> Diseño | D56: =IF(ISBLANK(Plan!C52),"",Plan!C52) -> Realizar diagramas de Casos de Uso | E56: =IF(ISBLANK(Plan!B55),"",IF(Plan!N55>0,Plan!N55,"")) -> 5
C57: =IF(ISBLANK(Plan!B53),"",Plan!B53) -> Diseño | D57: =IF(ISBLANK(Plan!C53),"",Plan!C53) -> Realizar modelo Entidad/Relación y BBDD | E57: =IF(ISBLANK(Plan!B56),"",IF(Plan!N56>0,Plan!N56,"")) -> 20
C58: =IF(ISBLANK(Plan!B54),"",Plan!B54) -> Diseño | D58: =IF(ISBLANK(Plan!C54),"",Plan!C54) -> Diseñar pantallas | E58: =IF(ISBLANK(Plan!B57),"",IF(Plan!N57>0,Plan!N57,""))
C59: =IF(ISBLANK(Plan!B55),"",Plan!B55) -> Diseño | D59: =IF(ISBLANK(Plan!C55),"",Plan!C55) -> Inspeccionar diseño (Q) y poner en línea base (GCS) | E59: =IF(ISBLANK(Plan!B58),"",IF(Plan!N58>0,Plan!N58,""))
C60: =IF(ISBLANK(Plan!B56),"",Plan!B56) -> Diseño | D60: =IF(ISBLANK(Plan!C56),"",Plan!C56) -> Introducir datos de Planificación/Monitorización S6 (esfuerzo real / semana, US) | E60: =IF(ISBLANK(Plan!B59),"",IF(Plan!N59>0,Plan!N59,""))
C61: =IF(ISBLANK(Plan!B57),"",Plan!B57) | D61: =IF(ISBLANK(Plan!C57),"",Plan!C57) | E61: =IF(ISBLANK(Plan!B60),"",IF(Plan!N60>0,Plan!N60,""))
C62: =IF(ISBLANK(Plan!B58),"",Plan!B58) | D62: =IF(ISBLANK(Plan!C58),"",Plan!C58) | E62: =IF(ISBLANK(Plan!B61),"",IF(Plan!N61>0,Plan!N61,""))
... C73: =IF(ISBLANK(Plan!B69),"",Plan!B69) -> Implementación | D73: =IF(ISBLANK(Plan!C69),"",Plan!C69) -> Registrar datos de calidad S7: ejecucion, defectos y verificacion DoD | E73: =IF(ISBLANK(Plan!B72),"",IF(Plan!N72>0,Plan!N72,""))
C74: =IF(ISBLANK(Plan!#REF!),"",Plan!#REF!) -> #REF! | D74: =IF(ISBLANK(Plan!#REF!),"",Plan!#REF!) -> #REF! | E74: =IF(ISBLANK(Plan!B73),"",IF(Plan!N73>0,Plan!N73,""))
C75: =IF(ISBLANK(Plan!B70),"",Plan!B70) | D75: =IF(ISBLANK(Plan!C70),"",Plan!C70) | E75: =IF(ISBLANK(Plan!B74),"",IF(Plan!N74>0,Plan!N74,""))
C76: =IF(ISBLANK(Plan!B71),"",Plan!B71) | D76: =IF(ISBLANK(Plan!C71),"",Plan!C71) | E76: =IF(ISBLANK(Plan!B75),"",IF(Plan!N75>0,Plan!N75,""))
C77: =IF(ISBLANK(Plan!B72),"",Plan!B72) -> Pruebas | D77: =IF(ISBLANK(Plan!C72),"",Plan!C72) -> Definir casos de prueba unitarios y de aceptación por US | E77: =IF(ISBLANK(Plan!B76),"",IF(Plan!N76>0,Plan!N76,""))
C78: =IF(ISBLANK(Plan!B73),"",Plan!B73) -> Pruebas | D78: =IF(ISBLANK(Plan!C73),"",Plan!C73) -> Ejecutar pruebas y registrar resultado esperado vs real y version | E78: =IF(ISBLANK(Plan!B77),"",IF(Plan!N77>0,Plan!N77,""))
C79: =IF(ISBLANK(Plan!B74),"",Plan!B74) -> Pruebas | D79: =IF(ISBLANK(Plan!C74),"",Plan!C74) -> Inspeccionar registros de pruebas, enlazar evidencias y poner en linea base (Q/GCS) | E79: =IF(ISBLANK(Plan!B78),"",IF(Plan!N78>0,Plan!N78,""))
C80: =IF(ISBLANK(Plan!B75),"",Plan!B75) -> Pruebas | D80: =IF(ISBLANK(Plan!C75),"",Plan!C75) -> Introducir datos de Planificación/Monitorización S8 (esfuerzo real / semana, US) | E80: =IF(ISBLANK(Plan!B79),"",IF(Plan!N79>0,Plan!N79,""))
C81: =IF(ISBLANK(Plan!B76),"",Plan!B76) | D81: =IF(ISBLANK(Plan!C76),"",Plan!C76) | E81: =IF(ISBLANK(Plan!B80),"",IF(Plan!N80>0,Plan!N80,""))
C82: =IF(ISBLANK(Plan!B77),"",Plan!B77) | D82: =IF(ISBLANK(Plan!C77),"",Plan!C77) | E82: =IF(ISBLANK(Plan!B81),"",IF(Plan!N81>0,Plan!N81,""))
C83: =IF(ISBLANK(Plan!B78),"",Plan!B78) -> Retrospectiva | D83: =IF(ISBLANK(Plan!C78),"",Plan!C78) -> Realizar informe de retrospectiva del Sprint 1 | E83: =IF(ISBLANK(Plan!B82),"",IF(Plan!N82>0,Plan!N82,""))
C84: =IF(ISBLANK(Plan!B79),"",Plan!B79) -> Retrospectiva | D84: =IF(ISBLANK(Plan!C79),"",Plan!C79) -> Evaluar roles y equipo del Sprint 1 | E84: =IF(ISBLANK(Plan!B83),"",IF(Plan!N83>0,Plan!N83,""))
C85: =IF(ISBLANK(Plan!B80),"",Plan!B80) -> Retrospectiva | D85: =IF(ISBLANK(Plan!C80),"",Plan!C80) -> Revisar productos y procesos; dificultades, PF y PD | E85: =IF(ISBLANK(Plan!B84),"",IF(Plan!N84>0,Plan!N84,""))
C86: =IF(ISBLANK(Plan!B81),"",Plan!B81) -> Retrospectiva | D86: =IF(ISBLANK(Plan!C81),"",Plan!C81) -> Retrospectiva STARFISH (Keep / More / Start / Stop / Less) | E86: =IF(ISBLANK(Plan!B85),"",IF(Plan!N85>0,Plan!N85,""))
... C88: =IF(ISBLANK(Plan!B83),"",Plan!B83) -> Retrospectiva | D88: =IF(ISBLANK(Plan!C83),"",Plan!C83) -> Lecciones aprendidas y mejoras al proceso | E88: =IF(ISBLANK(Plan!B87),"",IF(Plan!N87>0,Plan!N87,""))
E89: =IF(ISBLANK(Plan!B88),"",IF(Plan!N88>0,Plan!N88,""))
E90: =IF(ISBLANK(Plan!B89),"",IF(Plan!N89>0,Plan!N89,""))

Sheet Planificacion
C2: Lista de tareas de Planificación | G2: IMPORTANTE
D3: Total min. reales | E3: =SUM(E6:E88) -> 505 | G3: ¡ NO EDITAR ESTA PÁGINA ! Se genera automaticamente
C5: Fase | D5: Actividad | E5: Esfuerzo (minutos reales)
C6: =IF(ISBLANK(Plan!B5),"",Plan!B5) -> Lanzamiento | D6: =IF(ISBLANK(Plan!C5),"",Plan!C5) -> Asignar equipos y roles | E6: =IF(ISBLANK(Plan!B5),"",IF(Plan!O5>0,Plan!O5,"")) -> 10
C7: =IF(ISBLANK(Plan!B6),"",Plan!B6) -> Lanzamiento | D7: =IF(ISBLANK(Plan!C6),"",Plan!C6) -> Definir proceso de reuniones | E7: =IF(ISBLANK(Plan!B6),"",IF(Plan!O6>0,Plan!O6,"")) -> 20
C8: =IF(ISBLANK(Plan!B7),"",Plan!B7) -> Lanzamiento | D8: =IF(ISBLANK(Plan!C7),"",Plan!C7) -> Realizar Estándar de Documentación | E8: =IF(ISBLANK(Plan!B7),"",IF(Plan!O7>0,Plan!O7,""))
C9: =IF(ISBLANK(Plan!B8),"",Plan!B8) -> Lanzamiento | D9: =IF(ISBLANK(Plan!C8),"",Plan!C8) -> Realizar Estándar de Agendas | E9: =IF(ISBLANK(Plan!B8),"",IF(Plan!O8>0,Plan!O8,"")) -> 15
C10: =IF(ISBLANK(Plan!B9),"",Plan!B9) -> Lanzamiento | D10: =IF(ISBLANK(Plan!C9),"",Plan!C9) -> Realizar Estándar de Actas | E10: =IF(ISBLANK(Plan!B9),"",IF(Plan!O9>0,Plan!O9,""))
C11: =IF(ISBLANK(Plan!B10),"",Plan!B10) -> Lanzamiento | D11: =IF(ISBLANK(Plan!C10),"",Plan!C10) -> Definir Ciclo de Vida a aplicar (actividades) | E11: =IF(ISBLANK(Plan!B10),"",IF(Plan!O10>0,Plan!O10,"")) -> 15
C12: =IF(ISBLANK(Plan!B11),"",Plan!B11) -> Lanzamiento | D12: =IF(ISBLANK(Plan!C11),"",Plan!C11) -> Definir outputs y plantillas del CV | E12: =IF(ISBLANK(Plan!B11),"",IF(Plan!O11>0,Plan!O11,""))
C13: =IF(ISBLANK(Plan!B12),"",Plan!B12) -> Lanzamiento | D13: =IF(ISBLANK(Plan!C12),"",Plan!C12) -> Definir Entorno de Desarrollo | E13: =IF(ISBLANK(Plan!B12),"",IF(Plan!O12>0,Plan!O12,"")) -> 20
C14: =IF(ISBLANK(Plan!B13),"",Plan!B13) -> Lanzamiento | D14: =IF(ISBLANK(Plan!C13),"",Plan!C13) -> Configurar Entorno de Desarrollo | E14: =IF(ISBLANK(Plan!B13),"",IF(Plan!O13>0,Plan!O13,""))
C15: =IF(ISBLANK(Plan!B14),"",Plan!B14) -> Lanzamiento | D15: =IF(ISBLANK(Plan!C14),"",Plan!C14) -> Definir Estándar de Codificación | E15: =IF(ISBLANK(Plan!B14),"",IF(Plan!O14>0,Plan!O14,"")) -> 15
E16: =IF(ISBLANK(Plan!B15),"",IF(Plan!O15>0,Plan!O15,"")) -> 5
E17: =IF(ISBLANK(Plan!B16),"",IF(Plan!O16>0,Plan!O16,""))
C18: =IF(ISBLANK(Plan!B15),"",Plan!B15) -> Lanzamiento | D18: =IF(ISBLANK(Plan!C15),"",Plan!C15) -> Introducir datos de Planificación/Monitorización S1 (esfuerzo real / semana) | E18: =IF(ISBLANK(Plan!B17),"",IF(Plan!O17>0,Plan!O17,""))
C19: =IF(ISBLANK(Plan!B16),"",Plan!B16) | D19: =IF(ISBLANK(Plan!C16),"",Plan!C16) | E19: =IF(ISBLANK(Plan!B18),"",IF(Plan!O18>0,Plan!O18,""))
C20: =IF(ISBLANK(Plan!B17),"",Plan!B17) | D20: =IF(ISBLANK(Plan!C17),"",Plan!C17) | E20: =IF(ISBLANK(Plan!B19),"",IF(Plan!O19>0,Plan!O19,"")) -> 30
C21: =IF(ISBLANK(Plan!B18),"",Plan!B18) | D21: =IF(ISBLANK(Plan!C18),"",Plan!C18) | E21: =IF(ISBLANK(Plan!B20),"",IF(Plan!O20>0,Plan!O20,"")) -> 5
C22: =IF(ISBLANK(Plan!B19),"",Plan!B19) -> Requisitos | D22: =IF(ISBLANK(Plan!C19),"",Plan!C19) -> Obtener Historias de Usuario (US) | E22: =IF(ISBLANK(Plan!B21),"",IF(Plan!O21>0,Plan!O21,""))
C23: =IF(ISBLANK(Plan!B20),"",Plan!B20) -> Requisitos | D23: =IF(ISBLANK(Plan!C20),"",Plan!C20) -> Describir las US según plantilla (Como/Quiero/Para + criterios de aceptación) | E23: =IF(ISBLANK(Plan!B22),"",IF(Plan!O22>0,Plan!O22,"")) -> 10
C24: =IF(ISBLANK(Plan!B21),"",Plan!B21) -> Requisitos | D24: =IF(ISBLANK(Plan!C21),"",Plan!C21) -> Completar campos de US para puntos de función | E24: =IF(ISBLANK(Plan!B23),"",IF(Plan!O23>0,Plan!O23,"")) -> 60
C25: =IF(ISBLANK(Plan!B22),"",Plan!B22) -> Requisitos | D25: =IF(ISBLANK(Plan!C22),"",Plan!C22) -> Elaborar Product Backlog priorizado | E25: =IF(ISBLANK(Plan!B24),"",IF(Plan!O24>0,Plan!O24,"")) -> 5
C26: =IF(ISBLANK(Plan!B23),"",Plan!B23) -> Requisitos | D26: =IF(ISBLANK(Plan!C23),"",Plan!C23) -> Inspeccionar las US y criterios de aceptacion (Q) | E26: =IF(ISBLANK(Plan!B25),"",IF(Plan!O25>0,Plan!O25,""))
C27: =IF(ISBLANK(Plan!B24),"",Plan!B24) -> Requisitos | D27: =IF(ISBLANK(Plan!C24),"",Plan!C24) -> Poner en línea base las US (GCS) | E27: =IF(ISBLANK(Plan!B26),"",IF(Plan!O26>0,Plan!O26,"")) -> 10
C28: =IF(ISBLANK(Plan!B25),"",Plan!B25) -> Requisitos | D28: =IF(ISBLANK(Plan!C25),"",Plan!C25) -> Introducir datos de Planificación/Monitorización(esfuerzo real / semana) S3 | E28: =IF(ISBLANK(Plan!B27),"",IF(Plan!O27>0,Plan!O27,""))
C29: =IF(ISBLANK(Plan!B26),"",Plan!B26) -> Requisitos | D29: =IF(ISBLANK(Plan!C26),"",Plan!C26) -> Registrar datos de calidad S3 | E29: =IF(ISBLANK(Plan!B28),"",IF(Plan!O28>0,Plan!O28,""))
... C49: =IF(ISBLANK(Plan!B46),"",Plan!B46) -> Planificación | D49: =IF(ISBLANK(Plan!C46),"",Plan!C46) -> Realizar Diagrama de Gantt del Sprint 1 | E49: =IF(ISBLANK(Plan!B48),"",IF(Plan!O48>0,Plan!O48,"")) -> 5
C50: =IF(ISBLANK(Plan!#REF!),"",Plan!#REF!) -> #REF! | D50: =IF(ISBLANK(Plan!#REF!),"",Plan!#REF!) -> #REF! | E50: =IF(ISBLANK(Plan!B49),"",IF(Plan!O49>0,Plan!O49,""))
C51: =IF(ISBLANK(Plan!B47),"",Plan!B47) -> Planificación | D51: =IF(ISBLANK(Plan!C47),"",Plan!C47) -> Inspeccionar planes (Q) y poner en línea base (GCS) | E51: =IF(ISBLANK(Plan!B50),"",IF(Plan!O50>0,Plan!O50,""))
C52: =IF(ISBLANK(Plan!B48),"",Plan!B48) -> Planificación | D52: =IF(ISBLANK(Plan!C48),"",Plan!C48) -> Introducir datos de Planificación/Monitorización S5 (esfuerzo real / semana) | E52: =IF(ISBLANK(Plan!B51),"",IF(Plan!O51>0,Plan!O51,""))
C53: =IF(ISBLANK(Plan!B49),"",Plan!B49) -> Planificación | D53: =IF(ISBLANK(Plan!C49),"",Plan!C49) -> Registrar datos de calidad S5: revisiones, pruebas y defectos | E53: =IF(ISBLANK(Plan!B52),"",IF(Plan!O52>0,Plan!O52,"")) -> 5
C54: =IF(ISBLANK(Plan!B50),"",Plan!B50) | D54: =IF(ISBLANK(Plan!C50),"",Plan!C50) | E54: =IF(ISBLANK(Plan!B53),"",IF(Plan!O53>0,Plan!O53,""))
C55: =IF(ISBLANK(Plan!B51),"",Plan!B51) | D55: =IF(ISBLANK(Plan!C51),"",Plan!C51) | E55: =IF(ISBLANK(Plan!B54),"",IF(Plan!O54>0,Plan!O54,""))
C56: =IF(ISBLANK(Plan!B52),"",Plan!B52) -> Diseño | D56: =IF(ISBLANK(Plan!C52),"",Plan!C52) -> Realizar diagramas de Casos de Uso | E56: =IF(ISBLANK(Plan!B55),"",IF(Plan!O55>0,Plan!O55,"")) -> 5
C57: =IF(ISBLANK(Plan!B53),"",Plan!B53) -> Diseño | D57: =IF(ISBLANK(Plan!C53),"",Plan!C53) -> Realizar modelo Entidad/Relación y BBDD | E57: =IF(ISBLANK(Plan!B56),"",IF(Plan!O56>0,Plan!O56,"")) -> 60
C58: =IF(ISBLANK(Plan!B54),"",Plan!B54) -> Diseño | D58: =IF(ISBLANK(Plan!C54),"",Plan!C54) -> Diseñar pantallas | E58: =IF(ISBLANK(Plan!B57),"",IF(Plan!O57>0,Plan!O57,""))
C59: =IF(ISBLANK(Plan!B55),"",Plan!B55) -> Diseño | D59: =IF(ISBLANK(Plan!C55),"",Plan!C55) -> Inspeccionar diseño (Q) y poner en línea base (GCS) | E59: =IF(ISBLANK(Plan!B58),"",IF(Plan!O58>0,Plan!O58,""))
C60: =IF(ISBLANK(Plan!B56),"",Plan!B56) -> Diseño | D60: =IF(ISBLANK(Plan!C56),"",Plan!C56) -> Introducir datos de Planificación/Monitorización S6 (esfuerzo real / semana, US) | E60: =IF(ISBLANK(Plan!B59),"",IF(Plan!O59>0,Plan!O59,""))
C61: =IF(ISBLANK(Plan!B57),"",Plan!B57) | D61: =IF(ISBLANK(Plan!C57),"",Plan!C57) | E61: =IF(ISBLANK(Plan!B60),"",IF(Plan!O60>0,Plan!O60,""))
C62: =IF(ISBLANK(Plan!B58),"",Plan!B58) | D62: =IF(ISBLANK(Plan!C58),"",Plan!C58) | E62: =IF(ISBLANK(Plan!B61),"",IF(Plan!O61>0,Plan!O61,""))
... C73: =IF(ISBLANK(Plan!B69),"",Plan!B69) -> Implementación | D73: =IF(ISBLANK(Plan!C69),"",Plan!C69) -> Registrar datos de calidad S7: ejecucion, defectos y verificacion DoD | E73: =IF(ISBLANK(Plan!B72),"",IF(Plan!O72>0,Plan!O72,""))
C74: =IF(ISBLANK(Plan!#REF!),"",Plan!#REF!) -> #REF! | D74: =IF(ISBLANK(Plan!#REF!),"",Plan!#REF!) -> #REF! | E74: =IF(ISBLANK(Plan!B73),"",IF(Plan!O73>0,Plan!O73,""))
C75: =IF(ISBLANK(Plan!B70),"",Plan!B70) | D75: =IF(ISBLANK(Plan!C70),"",Plan!C70) | E75: =IF(ISBLANK(Plan!B74),"",IF(Plan!O74>0,Plan!O74,""))
C76: =IF(ISBLANK(Plan!B71),"",Plan!B71) | D76: =IF(ISBLANK(Plan!C71),"",Plan!C71) | E76: =IF(ISBLANK(Plan!B75),"",IF(Plan!O75>0,Plan!O75,""))
C77: =IF(ISBLANK(Plan!B72),"",Plan!B72) -> Pruebas | D77: =IF(ISBLANK(Plan!C72),"",Plan!C72) -> Definir casos de prueba unitarios y de aceptación por US | E77: =IF(ISBLANK(Plan!B76),"",IF(Plan!O76>0,Plan!O76,""))
C78: =IF(ISBLANK(Plan!B73),"",Plan!B73) -> Pruebas | D78: =IF(ISBLANK(Plan!C73),"",Plan!C73) -> Ejecutar pruebas y registrar resultado esperado vs real y version | E78: =IF(ISBLANK(Plan!B77),"",IF(Plan!O77>0,Plan!O77,""))
C79: =IF(ISBLANK(Plan!B74),"",Plan!B74) -> Pruebas | D79: =IF(ISBLANK(Plan!C74),"",Plan!C74) -> Inspeccionar registros de pruebas, enlazar evidencias y poner en linea base (Q/GCS) | E79: =IF(ISBLANK(Plan!B78),"",IF(Plan!O78>0,Plan!O78,""))
C80: =IF(ISBLANK(Plan!B75),"",Plan!B75) -> Pruebas | D80: =IF(ISBLANK(Plan!C75),"",Plan!C75) -> Introducir datos de Planificación/Monitorización S8 (esfuerzo real / semana, US) | E80: =IF(ISBLANK(Plan!B79),"",IF(Plan!O79>0,Plan!O79,""))
C81: =IF(ISBLANK(Plan!B76),"",Plan!B76) | D81: =IF(ISBLANK(Plan!C76),"",Plan!C76) | E81: =IF(ISBLANK(Plan!B80),"",IF(Plan!O80>0,Plan!O80,""))
C82: =IF(ISBLANK(Plan!B77),"",Plan!B77) | D82: =IF(ISBLANK(Plan!C77),"",Plan!C77) | E82: =IF(ISBLANK(Plan!B81),"",IF(Plan!O81>0,Plan!O81,""))
C83: =IF(ISBLANK(Plan!B78),"",Plan!B78) -> Retrospectiva | D83: =IF(ISBLANK(Plan!C78),"",Plan!C78) -> Realizar informe de retrospectiva del Sprint 1 | E83: =IF(ISBLANK(Plan!B82),"",IF(Plan!O82>0,Plan!O82,""))
C84: =IF(ISBLANK(Plan!B79),"",Plan!B79) -> Retrospectiva | D84: =IF(ISBLANK(Plan!C79),"",Plan!C79) -> Evaluar roles y equipo del Sprint 1 | E84: =IF(ISBLANK(Plan!B83),"",IF(Plan!O83>0,Plan!O83,""))
C85: =IF(ISBLANK(Plan!B80),"",Plan!B80) -> Retrospectiva | D85: =IF(ISBLANK(Plan!C80),"",Plan!C80) -> Revisar productos y procesos; dificultades, PF y PD | E85: =IF(ISBLANK(Plan!B84),"",IF(Plan!O84>0,Plan!O84,""))
C86: =IF(ISBLANK(Plan!B81),"",Plan!B81) -> Retrospectiva | D86: =IF(ISBLANK(Plan!C81),"",Plan!C81) -> Retrospectiva STARFISH (Keep / More / Start / Stop / Less) | E86: =IF(ISBLANK(Plan!B85),"",IF(Plan!O85>0,Plan!O85,""))
... C88: =IF(ISBLANK(Plan!B83),"",Plan!B83) -> Retrospectiva | D88: =IF(ISBLANK(Plan!C83),"",Plan!C83) -> Lecciones aprendidas y mejoras al proceso | E88: =IF(ISBLANK(Plan!B87),"",IF(Plan!O87>0,Plan!O87,""))
E89: =IF(ISBLANK(Plan!B88),"",IF(Plan!O88>0,Plan!O88,""))
E90: =IF(ISBLANK(Plan!B89),"",IF(Plan!O89>0,Plan!O89,""))
E91: =IF(ISBLANK(Plan!B90),"",IF(Plan!O90>0,Plan!O90,""))
E92: =IF(ISBLANK(Plan!B91),"",IF(Plan!O91>0,Plan!O91,""))
E93: =IF(ISBLANK(Plan!B92),"",IF(Plan!O92>0,Plan!O92,""))
E94: =IF(ISBLANK(Plan!B93),"",IF(Plan!O93>0,Plan!O93,""))
E95: =IF(ISBLANK(Plan!B94),"",IF(Plan!O94>0,Plan!O94,""))

Sheet Desarrollo
C2: Lista de tareas de Desarrollo | G2: IMPORTANTE
D3: Total min. reales | E3: =SUM(E6:E88) -> #REF! | G3: ¡ NO EDITAR ESTA PÁGINA ! Se genera automaticamente
C5: Fase | D5: Actividad | E5: Esfuerzo (minutos reales)
C6: =IF(ISBLANK(Plan!B5),"",Plan!B5) -> Lanzamiento | D6: =IF(ISBLANK(Plan!C5),"",Plan!C5) -> Asignar equipos y roles | E6: =IF(ISBLANK(Plan!B5),"",IF(Plan!P5>0,Plan!P5,"")) -> 10
C7: =IF(ISBLANK(Plan!B6),"",Plan!B6) -> Lanzamiento | D7: =IF(ISBLANK(Plan!C6),"",Plan!C6) -> Definir proceso de reuniones | E7: =IF(ISBLANK(Plan!B6),"",IF(Plan!P6>0,Plan!P6,"")) -> 20
C8: =IF(ISBLANK(Plan!B7),"",Plan!B7) -> Lanzamiento | D8: =IF(ISBLANK(Plan!C7),"",Plan!C7) -> Realizar Estándar de Documentación | E8: =IF(ISBLANK(Plan!B7),"",IF(Plan!P7>0,Plan!P7,""))
C9: =IF(ISBLANK(Plan!B8),"",Plan!B8) -> Lanzamiento | D9: =IF(ISBLANK(Plan!C8),"",Plan!C8) -> Realizar Estándar de Agendas | E9: =IF(ISBLANK(Plan!B8),"",IF(Plan!P8>0,Plan!P8,"")) -> 15
C10: =IF(ISBLANK(Plan!B9),"",Plan!B9) -> Lanzamiento | D10: =IF(ISBLANK(Plan!C9),"",Plan!C9) -> Realizar Estándar de Actas | E10: =IF(ISBLANK(Plan!B9),"",IF(Plan!P9>0,Plan!P9,""))
C11: =IF(ISBLANK(Plan!B10),"",Plan!B10) -> Lanzamiento | D11: =IF(ISBLANK(Plan!C10),"",Plan!C10) -> Definir Ciclo de Vida a aplicar (actividades) | E11: =IF(ISBLANK(Plan!B10),"",IF(Plan!P10>0,Plan!P10,"")) -> 15
C12: =IF(ISBLANK(Plan!B11),"",Plan!B11) -> Lanzamiento | D12: =IF(ISBLANK(Plan!C11),"",Plan!C11) -> Definir outputs y plantillas del CV | E12: =IF(ISBLANK(Plan!B11),"",IF(Plan!P11>0,Plan!P11,""))
C13: =IF(ISBLANK(Plan!B12),"",Plan!B12) -> Lanzamiento | D13: =IF(ISBLANK(Plan!C12),"",Plan!C12) -> Definir Entorno de Desarrollo | E13: =IF(ISBLANK(Plan!B12),"",IF(Plan!P12>0,Plan!P12,"")) -> 20
C14: =IF(ISBLANK(Plan!B13),"",Plan!B13) -> Lanzamiento | D14: =IF(ISBLANK(Plan!C13),"",Plan!C13) -> Configurar Entorno de Desarrollo | E14: =IF(ISBLANK(Plan!B13),"",IF(Plan!P13>0,Plan!P13,""))
C15: =IF(ISBLANK(Plan!B14),"",Plan!B14) -> Lanzamiento | D15: =IF(ISBLANK(Plan!C14),"",Plan!C14) -> Definir Estándar de Codificación | E15: =IF(ISBLANK(Plan!B14),"",IF(Plan!P14>0,Plan!P14,"")) -> 15
C18: =IF(ISBLANK(Plan!B15),"",Plan!B15) -> Lanzamiento | D18: =IF(ISBLANK(Plan!C15),"",Plan!C15) -> Introducir datos de Planificación/Monitorización S1 (esfuerzo real / semana) | E18: =IF(ISBLANK(Plan!B15),"",IF(Plan!P15>0,Plan!P15,"")) -> 5
C19: =IF(ISBLANK(Plan!B16),"",Plan!B16) | D19: =IF(ISBLANK(Plan!C16),"",Plan!C16) | E19: =IF(ISBLANK(Plan!B16),"",IF(Plan!P16>0,Plan!P16,""))
C20: =IF(ISBLANK(Plan!B17),"",Plan!B17) | D20: =IF(ISBLANK(Plan!C17),"",Plan!C17) | E20: =IF(ISBLANK(Plan!B17),"",IF(Plan!P17>0,Plan!P17,""))
C21: =IF(ISBLANK(Plan!B18),"",Plan!B18) | D21: =IF(ISBLANK(Plan!C18),"",Plan!C18) | E21: =IF(ISBLANK(Plan!B18),"",IF(Plan!P18>0,Plan!P18,""))
C22: =IF(ISBLANK(Plan!B19),"",Plan!B19) -> Requisitos | D22: =IF(ISBLANK(Plan!C19),"",Plan!C19) -> Obtener Historias de Usuario (US) | E22: =IF(ISBLANK(Plan!B19),"",IF(Plan!P19>0,Plan!P19,"")) -> 30
C23: =IF(ISBLANK(Plan!B20),"",Plan!B20) -> Requisitos | D23: =IF(ISBLANK(Plan!C20),"",Plan!C20) -> Describir las US según plantilla (Como/Quiero/Para + criterios de aceptación) | E23: =IF(ISBLANK(Plan!B20),"",IF(Plan!P20>0,Plan!P20,"")) -> 5
C24: =IF(ISBLANK(Plan!B21),"",Plan!B21) -> Requisitos | D24: =IF(ISBLANK(Plan!C21),"",Plan!C21) -> Completar campos de US para puntos de función | E24: =IF(ISBLANK(Plan!B21),"",IF(Plan!P21>0,Plan!P21,"")) -> 180
C25: =IF(ISBLANK(Plan!B22),"",Plan!B22) -> Requisitos | D25: =IF(ISBLANK(Plan!C22),"",Plan!C22) -> Elaborar Product Backlog priorizado | E25: =IF(ISBLANK(Plan!B22),"",IF(Plan!P22>0,Plan!P22,"")) -> 10
C26: =IF(ISBLANK(Plan!B23),"",Plan!B23) -> Requisitos | D26: =IF(ISBLANK(Plan!C23),"",Plan!C23) -> Inspeccionar las US y criterios de aceptacion (Q) | E26: =IF(ISBLANK(Plan!B23),"",IF(Plan!P23>0,Plan!P23,"")) -> 60
C27: =IF(ISBLANK(Plan!B24),"",Plan!B24) -> Requisitos | D27: =IF(ISBLANK(Plan!C24),"",Plan!C24) -> Poner en línea base las US (GCS) | E27: =IF(ISBLANK(Plan!B24),"",IF(Plan!P24>0,Plan!P24,"")) -> 5
C28: =IF(ISBLANK(Plan!B25),"",Plan!B25) -> Requisitos | D28: =IF(ISBLANK(Plan!C25),"",Plan!C25) -> Introducir datos de Planificación/Monitorización(esfuerzo real / semana) S3 | E28: =IF(ISBLANK(Plan!B25),"",IF(Plan!P25>0,Plan!P25,"")) -> 120
C29: =IF(ISBLANK(Plan!B26),"",Plan!B26) -> Requisitos | D29: =IF(ISBLANK(Plan!C26),"",Plan!C26) -> Registrar datos de calidad S3 | E29: =IF(ISBLANK(Plan!B26),"",IF(Plan!P26>0,Plan!P26,"")) -> 10
... C49: =IF(ISBLANK(Plan!B46),"",Plan!B46) -> Planificación | D49: =IF(ISBLANK(Plan!C46),"",Plan!C46) -> Realizar Diagrama de Gantt del Sprint 1 | E49: =IF(ISBLANK(Plan!B46),"",IF(Plan!P46>0,Plan!P46,"")) -> 10
C50: =IF(ISBLANK(Plan!#REF!),"",Plan!#REF!) -> #REF! | D50: =IF(ISBLANK(Plan!#REF!),"",Plan!#REF!) -> #REF! | E50: =IF(ISBLANK(Plan!#REF!),"",IF(Plan!#REF!>0,Plan!#REF!,"")) -> #REF!
C51: =IF(ISBLANK(Plan!B47),"",Plan!B47) -> Planificación | D51: =IF(ISBLANK(Plan!C47),"",Plan!C47) -> Inspeccionar planes (Q) y poner en línea base (GCS) | E51: =IF(ISBLANK(Plan!B47),"",IF(Plan!P47>0,Plan!P47,""))
C52: =IF(ISBLANK(Plan!B48),"",Plan!B48) -> Planificación | D52: =IF(ISBLANK(Plan!C48),"",Plan!C48) -> Introducir datos de Planificación/Monitorización S5 (esfuerzo real / semana) | E52: =IF(ISBLANK(Plan!B48),"",IF(Plan!P48>0,Plan!P48,"")) -> 5
C53: =IF(ISBLANK(Plan!B49),"",Plan!B49) -> Planificación | D53: =IF(ISBLANK(Plan!C49),"",Plan!C49) -> Registrar datos de calidad S5: revisiones, pruebas y defectos | E53: =IF(ISBLANK(Plan!B49),"",IF(Plan!P49>0,Plan!P49,"")) -> 40
C54: =IF(ISBLANK(Plan!B50),"",Plan!B50) | D54: =IF(ISBLANK(Plan!C50),"",Plan!C50) | E54: =IF(ISBLANK(Plan!B50),"",IF(Plan!P50>0,Plan!P50,""))
C55: =IF(ISBLANK(Plan!B51),"",Plan!B51) | D55: =IF(ISBLANK(Plan!C51),"",Plan!C51) | E55: =IF(ISBLANK(Plan!B51),"",IF(Plan!P51>0,Plan!P51,""))
C56: =IF(ISBLANK(Plan!B52),"",Plan!B52) -> Diseño | D56: =IF(ISBLANK(Plan!C52),"",Plan!C52) -> Realizar diagramas de Casos de Uso | E56: =IF(ISBLANK(Plan!B52),"",IF(Plan!P52>0,Plan!P52,"")) -> 25
C57: =IF(ISBLANK(Plan!B53),"",Plan!B53) -> Diseño | D57: =IF(ISBLANK(Plan!C53),"",Plan!C53) -> Realizar modelo Entidad/Relación y BBDD | E57: =IF(ISBLANK(Plan!B53),"",IF(Plan!P53>0,Plan!P53,""))
C58: =IF(ISBLANK(Plan!B54),"",Plan!B54) -> Diseño | D58: =IF(ISBLANK(Plan!C54),"",Plan!C54) -> Diseñar pantallas | E58: =IF(ISBLANK(Plan!B54),"",IF(Plan!P54>0,Plan!P54,""))
C59: =IF(ISBLANK(Plan!B55),"",Plan!B55) -> Diseño | D59: =IF(ISBLANK(Plan!C55),"",Plan!C55) -> Inspeccionar diseño (Q) y poner en línea base (GCS) | E59: =IF(ISBLANK(Plan!B55),"",IF(Plan!P55>0,Plan!P55,"")) -> 5
C60: =IF(ISBLANK(Plan!B56),"",Plan!B56) -> Diseño | D60: =IF(ISBLANK(Plan!C56),"",Plan!C56) -> Introducir datos de Planificación/Monitorización S6 (esfuerzo real / semana, US) | E60: =IF(ISBLANK(Plan!B56),"",IF(Plan!P56>0,Plan!P56,"")) -> 10
C61: =IF(ISBLANK(Plan!B57),"",Plan!B57) | D61: =IF(ISBLANK(Plan!C57),"",Plan!C57) | E61: =IF(ISBLANK(Plan!B57),"",IF(Plan!P57>0,Plan!P57,""))
C62: =IF(ISBLANK(Plan!B58),"",Plan!B58) | D62: =IF(ISBLANK(Plan!C58),"",Plan!C58) | E62: =IF(ISBLANK(Plan!B58),"",IF(Plan!P58>0,Plan!P58,""))
... C73: =IF(ISBLANK(Plan!B69),"",Plan!B69) -> Implementación | D73: =IF(ISBLANK(Plan!C69),"",Plan!C69) -> Registrar datos de calidad S7: ejecucion, defectos y verificacion DoD | E73: =IF(ISBLANK(Plan!B69),"",IF(Plan!P69>0,Plan!P69,""))
C74: =IF(ISBLANK(Plan!#REF!),"",Plan!#REF!) -> #REF! | D74: =IF(ISBLANK(Plan!#REF!),"",Plan!#REF!) -> #REF! | E74: =IF(ISBLANK(Plan!#REF!),"",IF(Plan!#REF!>0,Plan!#REF!,"")) -> #REF!
C75: =IF(ISBLANK(Plan!B70),"",Plan!B70) | D75: =IF(ISBLANK(Plan!C70),"",Plan!C70) | E75: =IF(ISBLANK(Plan!B70),"",IF(Plan!P70>0,Plan!P70,""))
C76: =IF(ISBLANK(Plan!B71),"",Plan!B71) | D76: =IF(ISBLANK(Plan!C71),"",Plan!C71) | E76: =IF(ISBLANK(Plan!B71),"",IF(Plan!P71>0,Plan!P71,""))
C77: =IF(ISBLANK(Plan!B72),"",Plan!B72) -> Pruebas | D77: =IF(ISBLANK(Plan!C72),"",Plan!C72) -> Definir casos de prueba unitarios y de aceptación por US | E77: =IF(ISBLANK(Plan!B72),"",IF(Plan!P72>0,Plan!P72,""))
C78: =IF(ISBLANK(Plan!B73),"",Plan!B73) -> Pruebas | D78: =IF(ISBLANK(Plan!C73),"",Plan!C73) -> Ejecutar pruebas y registrar resultado esperado vs real y version | E78: =IF(ISBLANK(Plan!B73),"",IF(Plan!P73>0,Plan!P73,""))
C79: =IF(ISBLANK(Plan!B74),"",Plan!B74) -> Pruebas | D79: =IF(ISBLANK(Plan!C74),"",Plan!C74) -> Inspeccionar registros de pruebas, enlazar evidencias y poner en linea base (Q/GCS) | E79: =IF(ISBLANK(Plan!B74),"",IF(Plan!P74>0,Plan!P74,""))
C80: =IF(ISBLANK(Plan!B75),"",Plan!B75) -> Pruebas | D80: =IF(ISBLANK(Plan!C75),"",Plan!C75) -> Introducir datos de Planificación/Monitorización S8 (esfuerzo real / semana, US) | E80: =IF(ISBLANK(Plan!B75),"",IF(Plan!P75>0,Plan!P75,""))
C81: =IF(ISBLANK(Plan!B76),"",Plan!B76) | D81: =IF(ISBLANK(Plan!C76),"",Plan!C76) | E81: =IF(ISBLANK(Plan!B76),"",IF(Plan!P76>0,Plan!P76,""))
C82: =IF(ISBLANK(Plan!B77),"",Plan!B77) | D82: =IF(ISBLANK(Plan!C77),"",Plan!C77) | E82: =IF(ISBLANK(Plan!B77),"",IF(Plan!P77>0,Plan!P77,""))
C83: =IF(ISBLANK(Plan!B78),"",Plan!B78) -> Retrospectiva | D83: =IF(ISBLANK(Plan!C78),"",Plan!C78) -> Realizar informe de retrospectiva del Sprint 1 | E83: =IF(ISBLANK(Plan!B78),"",IF(Plan!P78>0,Plan!P78,""))
C84: =IF(ISBLANK(Plan!B79),"",Plan!B79) -> Retrospectiva | D84: =IF(ISBLANK(Plan!C79),"",Plan!C79) -> Evaluar roles y equipo del Sprint 1 | E84: =IF(ISBLANK(Plan!B79),"",IF(Plan!P79>0,Plan!P79,""))
C85: =IF(ISBLANK(Plan!B80),"",Plan!B80) -> Retrospectiva | D85: =IF(ISBLANK(Plan!C80),"",Plan!C80) -> Revisar productos y procesos; dificultades, PF y PD | E85: =IF(ISBLANK(Plan!B80),"",IF(Plan!P80>0,Plan!P80,""))
C86: =IF(ISBLANK(Plan!B81),"",Plan!B81) -> Retrospectiva | D86: =IF(ISBLANK(Plan!C81),"",Plan!C81) -> Retrospectiva STARFISH (Keep / More / Start / Stop / Less) | E86: =IF(ISBLANK(Plan!B81),"",IF(Plan!P81>0,Plan!P81,""))
... C88: =IF(ISBLANK(Plan!B83),"",Plan!B83) -> Retrospectiva | D88: =IF(ISBLANK(Plan!C83),"",Plan!C83) -> Lecciones aprendidas y mejoras al proceso | E88: =IF(ISBLANK(Plan!B83),"",IF(Plan!P83>0,Plan!P83,""))

Sheet Cambios
C2: Lista de tareas de Cambios | G2: IMPORTANTE
D3: Total min. reales | E3: =SUM(E6:E88) -> #REF! | G3: ¡ NO EDITAR ESTA PÁGINA ! Se genera automaticamente
C5: Fase | D5: Actividad | E5: Esfuerzo (minutos reales)
C6: =IF(ISBLANK(Plan!B5),"",Plan!B5) -> Lanzamiento | D6: =IF(ISBLANK(Plan!C5),"",Plan!C5) -> Asignar equipos y roles | E6: =IF(ISBLANK(Plan!B5),"",IF(Plan!Q5>0,Plan!Q5,"")) -> 10
C7: =IF(ISBLANK(Plan!B6),"",Plan!B6) -> Lanzamiento | D7: =IF(ISBLANK(Plan!C6),"",Plan!C6) -> Definir proceso de reuniones | E7: =IF(ISBLANK(Plan!B6),"",IF(Plan!Q6>0,Plan!Q6,"")) -> 20
C8: =IF(ISBLANK(Plan!B7),"",Plan!B7) -> Lanzamiento | D8: =IF(ISBLANK(Plan!C7),"",Plan!C7) -> Realizar Estándar de Documentación | E8: =IF(ISBLANK(Plan!B7),"",IF(Plan!Q7>0,Plan!Q7,""))
C9: =IF(ISBLANK(Plan!B8),"",Plan!B8) -> Lanzamiento | D9: =IF(ISBLANK(Plan!C8),"",Plan!C8) -> Realizar Estándar de Agendas | E9: =IF(ISBLANK(Plan!B8),"",IF(Plan!Q8>0,Plan!Q8,"")) -> 15
C10: =IF(ISBLANK(Plan!B9),"",Plan!B9) -> Lanzamiento | D10: =IF(ISBLANK(Plan!C9),"",Plan!C9) -> Realizar Estándar de Actas | E10: =IF(ISBLANK(Plan!B9),"",IF(Plan!Q9>0,Plan!Q9,""))
C11: =IF(ISBLANK(Plan!B10),"",Plan!B10) -> Lanzamiento | D11: =IF(ISBLANK(Plan!C10),"",Plan!C10) -> Definir Ciclo de Vida a aplicar (actividades) | E11: =IF(ISBLANK(Plan!B10),"",IF(Plan!Q10>0,Plan!Q10,"")) -> 15
C12: =IF(ISBLANK(Plan!B11),"",Plan!B11) -> Lanzamiento | D12: =IF(ISBLANK(Plan!C11),"",Plan!C11) -> Definir outputs y plantillas del CV | E12: =IF(ISBLANK(Plan!B11),"",IF(Plan!Q11>0,Plan!Q11,""))
C13: =IF(ISBLANK(Plan!B12),"",Plan!B12) -> Lanzamiento | D13: =IF(ISBLANK(Plan!C12),"",Plan!C12) -> Definir Entorno de Desarrollo | E13: =IF(ISBLANK(Plan!B12),"",IF(Plan!Q12>0,Plan!Q12,"")) -> 10
C14: =IF(ISBLANK(Plan!B13),"",Plan!B13) -> Lanzamiento | D14: =IF(ISBLANK(Plan!C13),"",Plan!C13) -> Configurar Entorno de Desarrollo | E14: =IF(ISBLANK(Plan!B13),"",IF(Plan!Q13>0,Plan!Q13,""))
C15: =IF(ISBLANK(Plan!B14),"",Plan!B14) -> Lanzamiento | D15: =IF(ISBLANK(Plan!C14),"",Plan!C14) -> Definir Estándar de Codificación | E15: =IF(ISBLANK(Plan!B14),"",IF(Plan!Q14>0,Plan!Q14,"")) -> 10
C18: =IF(ISBLANK(Plan!B15),"",Plan!B15) -> Lanzamiento | D18: =IF(ISBLANK(Plan!C15),"",Plan!C15) -> Introducir datos de Planificación/Monitorización S1 (esfuerzo real / semana) | E18: =IF(ISBLANK(Plan!B15),"",IF(Plan!Q15>0,Plan!Q15,"")) -> 5
C19: =IF(ISBLANK(Plan!B16),"",Plan!B16) | D19: =IF(ISBLANK(Plan!C16),"",Plan!C16) | E19: =IF(ISBLANK(Plan!B16),"",IF(Plan!Q16>0,Plan!Q16,""))
C20: =IF(ISBLANK(Plan!B17),"",Plan!B17) | D20: =IF(ISBLANK(Plan!C17),"",Plan!C17) | E20: =IF(ISBLANK(Plan!B17),"",IF(Plan!Q17>0,Plan!Q17,""))
C21: =IF(ISBLANK(Plan!B18),"",Plan!B18) | D21: =IF(ISBLANK(Plan!C18),"",Plan!C18) | E21: =IF(ISBLANK(Plan!B18),"",IF(Plan!Q18>0,Plan!Q18,""))
C22: =IF(ISBLANK(Plan!B19),"",Plan!B19) -> Requisitos | D22: =IF(ISBLANK(Plan!C19),"",Plan!C19) -> Obtener Historias de Usuario (US) | E22: =IF(ISBLANK(Plan!B19),"",IF(Plan!Q19>0,Plan!Q19,""))
C23: =IF(ISBLANK(Plan!B20),"",Plan!B20) -> Requisitos | D23: =IF(ISBLANK(Plan!C20),"",Plan!C20) -> Describir las US según plantilla (Como/Quiero/Para + criterios de aceptación) | E23: =IF(ISBLANK(Plan!B20),"",IF(Plan!Q20>0,Plan!Q20,""))
C24: =IF(ISBLANK(Plan!B21),"",Plan!B21) -> Requisitos | D24: =IF(ISBLANK(Plan!C21),"",Plan!C21) -> Completar campos de US para puntos de función | E24: =IF(ISBLANK(Plan!B21),"",IF(Plan!Q21>0,Plan!Q21,""))
C25: =IF(ISBLANK(Plan!B22),"",Plan!B22) -> Requisitos | D25: =IF(ISBLANK(Plan!C22),"",Plan!C22) -> Elaborar Product Backlog priorizado | E25: =IF(ISBLANK(Plan!B22),"",IF(Plan!Q22>0,Plan!Q22,""))
C26: =IF(ISBLANK(Plan!B23),"",Plan!B23) -> Requisitos | D26: =IF(ISBLANK(Plan!C23),"",Plan!C23) -> Inspeccionar las US y criterios de aceptacion (Q) | E26: =IF(ISBLANK(Plan!B23),"",IF(Plan!Q23>0,Plan!Q23,""))
C27: =IF(ISBLANK(Plan!B24),"",Plan!B24) -> Requisitos | D27: =IF(ISBLANK(Plan!C24),"",Plan!C24) -> Poner en línea base las US (GCS) | E27: =IF(ISBLANK(Plan!B24),"",IF(Plan!Q24>0,Plan!Q24,""))
C28: =IF(ISBLANK(Plan!B25),"",Plan!B25) -> Requisitos | D28: =IF(ISBLANK(Plan!C25),"",Plan!C25) -> Introducir datos de Planificación/Monitorización(esfuerzo real / semana) S3 | E28: =IF(ISBLANK(Plan!B25),"",IF(Plan!Q25>0,Plan!Q25,""))
C29: =IF(ISBLANK(Plan!B26),"",Plan!B26) -> Requisitos | D29: =IF(ISBLANK(Plan!C26),"",Plan!C26) -> Registrar datos de calidad S3 | E29: =IF(ISBLANK(Plan!B26),"",IF(Plan!Q26>0,Plan!Q26,""))
... C49: =IF(ISBLANK(Plan!B46),"",Plan!B46) -> Planificación | D49: =IF(ISBLANK(Plan!C46),"",Plan!C46) -> Realizar Diagrama de Gantt del Sprint 1 | E49: =IF(ISBLANK(Plan!B46),"",IF(Plan!Q46>0,Plan!Q46,""))
C50: =IF(ISBLANK(Plan!#REF!),"",Plan!#REF!) -> #REF! | D50: =IF(ISBLANK(Plan!#REF!),"",Plan!#REF!) -> #REF! | E50: =IF(ISBLANK(Plan!#REF!),"",IF(Plan!#REF!>0,Plan!#REF!,"")) -> #REF!
C51: =IF(ISBLANK(Plan!B47),"",Plan!B47) -> Planificación | D51: =IF(ISBLANK(Plan!C47),"",Plan!C47) -> Inspeccionar planes (Q) y poner en línea base (GCS) | E51: =IF(ISBLANK(Plan!B47),"",IF(Plan!Q47>0,Plan!Q47,""))
C52: =IF(ISBLANK(Plan!B48),"",Plan!B48) -> Planificación | D52: =IF(ISBLANK(Plan!C48),"",Plan!C48) -> Introducir datos de Planificación/Monitorización S5 (esfuerzo real / semana) | E52: =IF(ISBLANK(Plan!B48),"",IF(Plan!Q48>0,Plan!Q48,""))
C53: =IF(ISBLANK(Plan!B49),"",Plan!B49) -> Planificación | D53: =IF(ISBLANK(Plan!C49),"",Plan!C49) -> Registrar datos de calidad S5: revisiones, pruebas y defectos | E53: =IF(ISBLANK(Plan!B49),"",IF(Plan!Q49>0,Plan!Q49,""))
C54: =IF(ISBLANK(Plan!B50),"",Plan!B50) | D54: =IF(ISBLANK(Plan!C50),"",Plan!C50) | E54: =IF(ISBLANK(Plan!B50),"",IF(Plan!Q50>0,Plan!Q50,""))
C55: =IF(ISBLANK(Plan!B51),"",Plan!B51) | D55: =IF(ISBLANK(Plan!C51),"",Plan!C51) | E55: =IF(ISBLANK(Plan!B51),"",IF(Plan!Q51>0,Plan!Q51,""))
C56: =IF(ISBLANK(Plan!B52),"",Plan!B52) -> Diseño | D56: =IF(ISBLANK(Plan!C52),"",Plan!C52) -> Realizar diagramas de Casos de Uso | E56: =IF(ISBLANK(Plan!B52),"",IF(Plan!Q52>0,Plan!Q52,""))
C57: =IF(ISBLANK(Plan!B53),"",Plan!B53) -> Diseño | D57: =IF(ISBLANK(Plan!C53),"",Plan!C53) -> Realizar modelo Entidad/Relación y BBDD | E57: =IF(ISBLANK(Plan!B53),"",IF(Plan!Q53>0,Plan!Q53,""))
C58: =IF(ISBLANK(Plan!B54),"",Plan!B54) -> Diseño | D58: =IF(ISBLANK(Plan!C54),"",Plan!C54) -> Diseñar pantallas | E58: =IF(ISBLANK(Plan!B54),"",IF(Plan!Q54>0,Plan!Q54,""))
C59: =IF(ISBLANK(Plan!B55),"",Plan!B55) -> Diseño | D59: =IF(ISBLANK(Plan!C55),"",Plan!C55) -> Inspeccionar diseño (Q) y poner en línea base (GCS) | E59: =IF(ISBLANK(Plan!B55),"",IF(Plan!Q55>0,Plan!Q55,""))
C60: =IF(ISBLANK(Plan!B56),"",Plan!B56) -> Diseño | D60: =IF(ISBLANK(Plan!C56),"",Plan!C56) -> Introducir datos de Planificación/Monitorización S6 (esfuerzo real / semana, US) | E60: =IF(ISBLANK(Plan!B56),"",IF(Plan!Q56>0,Plan!Q56,""))
C61: =IF(ISBLANK(Plan!B57),"",Plan!B57) | D61: =IF(ISBLANK(Plan!C57),"",Plan!C57) | E61: =IF(ISBLANK(Plan!B57),"",IF(Plan!Q57>0,Plan!Q57,""))
C62: =IF(ISBLANK(Plan!B58),"",Plan!B58) | D62: =IF(ISBLANK(Plan!C58),"",Plan!C58) | E62: =IF(ISBLANK(Plan!B58),"",IF(Plan!Q58>0,Plan!Q58,""))
... C73: =IF(ISBLANK(Plan!B69),"",Plan!B69) -> Implementación | D73: =IF(ISBLANK(Plan!C69),"",Plan!C69) -> Registrar datos de calidad S7: ejecucion, defectos y verificacion DoD | E73: =IF(ISBLANK(Plan!B69),"",IF(Plan!Q69>0,Plan!Q69,""))
C74: =IF(ISBLANK(Plan!#REF!),"",Plan!#REF!) -> #REF! | D74: =IF(ISBLANK(Plan!#REF!),"",Plan!#REF!) -> #REF! | E74: =IF(ISBLANK(Plan!#REF!),"",IF(Plan!#REF!>0,Plan!#REF!,"")) -> #REF!
C75: =IF(ISBLANK(Plan!B70),"",Plan!B70) | D75: =IF(ISBLANK(Plan!C70),"",Plan!C70) | E75: =IF(ISBLANK(Plan!B70),"",IF(Plan!Q70>0,Plan!Q70,""))
C76: =IF(ISBLANK(Plan!B71),"",Plan!B71) | D76: =IF(ISBLANK(Plan!C71),"",Plan!C71) | E76: =IF(ISBLANK(Plan!B71),"",IF(Plan!Q71>0,Plan!Q71,""))
C77: =IF(ISBLANK(Plan!B72),"",Plan!B72) -> Pruebas | D77: =IF(ISBLANK(Plan!C72),"",Plan!C72) -> Definir casos de prueba unitarios y de aceptación por US | E77: =IF(ISBLANK(Plan!B72),"",IF(Plan!Q72>0,Plan!Q72,""))
C78: =IF(ISBLANK(Plan!B73),"",Plan!B73) -> Pruebas | D78: =IF(ISBLANK(Plan!C73),"",Plan!C73) -> Ejecutar pruebas y registrar resultado esperado vs real y version | E78: =IF(ISBLANK(Plan!B73),"",IF(Plan!Q73>0,Plan!Q73,""))
C79: =IF(ISBLANK(Plan!B74),"",Plan!B74) -> Pruebas | D79: =IF(ISBLANK(Plan!C74),"",Plan!C74) -> Inspeccionar registros de pruebas, enlazar evidencias y poner en linea base (Q/GCS) | E79: =IF(ISBLANK(Plan!B74),"",IF(Plan!Q74>0,Plan!Q74,""))
C80: =IF(ISBLANK(Plan!B75),"",Plan!B75) -> Pruebas | D80: =IF(ISBLANK(Plan!C75),"",Plan!C75) -> Introducir datos de Planificación/Monitorización S8 (esfuerzo real / semana, US) | E80: =IF(ISBLANK(Plan!B75),"",IF(Plan!Q75>0,Plan!Q75,""))
C81: =IF(ISBLANK(Plan!B76),"",Plan!B76) | D81: =IF(ISBLANK(Plan!C76),"",Plan!C76) | E81: =IF(ISBLANK(Plan!B76),"",IF(Plan!Q76>0,Plan!Q76,""))
C82: =IF(ISBLANK(Plan!B77),"",Plan!B77) | D82: =IF(ISBLANK(Plan!C77),"",Plan!C77) | E82: =IF(ISBLANK(Plan!B77),"",IF(Plan!Q77>0,Plan!Q77,""))
C83: =IF(ISBLANK(Plan!B78),"",Plan!B78) -> Retrospectiva | D83: =IF(ISBLANK(Plan!C78),"",Plan!C78) -> Realizar informe de retrospectiva del Sprint 1 | E83: =IF(ISBLANK(Plan!B78),"",IF(Plan!Q78>0,Plan!Q78,""))
C84: =IF(ISBLANK(Plan!B79),"",Plan!B79) -> Retrospectiva | D84: =IF(ISBLANK(Plan!C79),"",Plan!C79) -> Evaluar roles y equipo del Sprint 1 | E84: =IF(ISBLANK(Plan!B79),"",IF(Plan!Q79>0,Plan!Q79,""))
C85: =IF(ISBLANK(Plan!B80),"",Plan!B80) -> Retrospectiva | D85: =IF(ISBLANK(Plan!C80),"",Plan!C80) -> Revisar productos y procesos; dificultades, PF y PD | E85: =IF(ISBLANK(Plan!B80),"",IF(Plan!Q80>0,Plan!Q80,""))
C86: =IF(ISBLANK(Plan!B81),"",Plan!B81) -> Retrospectiva | D86: =IF(ISBLANK(Plan!C81),"",Plan!C81) -> Retrospectiva STARFISH (Keep / More / Start / Stop / Less) | E86: =IF(ISBLANK(Plan!B81),"",IF(Plan!Q81>0,Plan!Q81,""))
... C88: =IF(ISBLANK(Plan!B83),"",Plan!B83) -> Retrospectiva | D88: =IF(ISBLANK(Plan!C83),"",Plan!C83) -> Lecciones aprendidas y mejoras al proceso | E88: =IF(ISBLANK(Plan!B83),"",IF(Plan!Q83>0,Plan!Q83,""))

Sheet Calidad
C2: Lista de tareas de Calidad | G2: IMPORTANTE
D3: Total min. reales | E3: =SUM(E6:E88) -> #REF! | G3: ¡ NO EDITAR ESTA PÁGINA ! Se genera automaticamente
C5: Fase | D5: Actividad | E5: Esfuerzo (minutos reales)
C6: =IF(ISBLANK(Plan!B5),"",Plan!B5) -> Lanzamiento | D6: =IF(ISBLANK(Plan!C5),"",Plan!C5) -> Asignar equipos y roles | E6: =IF(ISBLANK(Plan!B5),"",IF(Plan!R5>0,Plan!R5,"")) -> 10
C7: =IF(ISBLANK(Plan!B6),"",Plan!B6) -> Lanzamiento | D7: =IF(ISBLANK(Plan!C6),"",Plan!C6) -> Definir proceso de reuniones | E7: =IF(ISBLANK(Plan!B6),"",IF(Plan!R6>0,Plan!R6,"")) -> 20
C8: =IF(ISBLANK(Plan!B7),"",Plan!B7) -> Lanzamiento | D8: =IF(ISBLANK(Plan!C7),"",Plan!C7) -> Realizar Estándar de Documentación | E8: =IF(ISBLANK(Plan!B7),"",IF(Plan!R7>0,Plan!R7,"")) -> 20
C9: =IF(ISBLANK(Plan!B8),"",Plan!B8) -> Lanzamiento | D9: =IF(ISBLANK(Plan!C8),"",Plan!C8) -> Realizar Estándar de Agendas | E9: =IF(ISBLANK(Plan!B8),"",IF(Plan!R8>0,Plan!R8,"")) -> 10
C10: =IF(ISBLANK(Plan!B9),"",Plan!B9) -> Lanzamiento | D10: =IF(ISBLANK(Plan!C9),"",Plan!C9) -> Realizar Estándar de Actas | E10: =IF(ISBLANK(Plan!B9),"",IF(Plan!R9>0,Plan!R9,""))
C11: =IF(ISBLANK(Plan!B10),"",Plan!B10) -> Lanzamiento | D11: =IF(ISBLANK(Plan!C10),"",Plan!C10) -> Definir Ciclo de Vida a aplicar (actividades) | E11: =IF(ISBLANK(Plan!B10),"",IF(Plan!R10>0,Plan!R10,"")) -> 10
C12: =IF(ISBLANK(Plan!B11),"",Plan!B11) -> Lanzamiento | D12: =IF(ISBLANK(Plan!C11),"",Plan!C11) -> Definir outputs y plantillas del CV | E12: =IF(ISBLANK(Plan!B11),"",IF(Plan!R11>0,Plan!R11,""))
C13: =IF(ISBLANK(Plan!B12),"",Plan!B12) -> Lanzamiento | D13: =IF(ISBLANK(Plan!C12),"",Plan!C12) -> Definir Entorno de Desarrollo | E13: =IF(ISBLANK(Plan!B12),"",IF(Plan!R12>0,Plan!R12,"")) -> 15
C14: =IF(ISBLANK(Plan!B13),"",Plan!B13) -> Lanzamiento | D14: =IF(ISBLANK(Plan!C13),"",Plan!C13) -> Configurar Entorno de Desarrollo | E14: =IF(ISBLANK(Plan!B13),"",IF(Plan!R13>0,Plan!R13,""))
C15: =IF(ISBLANK(Plan!B14),"",Plan!B14) -> Lanzamiento | D15: =IF(ISBLANK(Plan!C14),"",Plan!C14) -> Definir Estándar de Codificación | E15: =IF(ISBLANK(Plan!B14),"",IF(Plan!R14>0,Plan!R14,"")) -> 10
C18: =IF(ISBLANK(Plan!B15),"",Plan!B15) -> Lanzamiento | D18: =IF(ISBLANK(Plan!C15),"",Plan!C15) -> Introducir datos de Planificación/Monitorización S1 (esfuerzo real / semana) | E18: =IF(ISBLANK(Plan!B15),"",IF(Plan!R15>0,Plan!R15,"")) -> 5
C19: =IF(ISBLANK(Plan!B16),"",Plan!B16) | D19: =IF(ISBLANK(Plan!C16),"",Plan!C16) | E19: =IF(ISBLANK(Plan!B16),"",IF(Plan!R16>0,Plan!R16,""))
C20: =IF(ISBLANK(Plan!B17),"",Plan!B17) | D20: =IF(ISBLANK(Plan!C17),"",Plan!C17) | E20: =IF(ISBLANK(Plan!B17),"",IF(Plan!R17>0,Plan!R17,""))
C21: =IF(ISBLANK(Plan!B18),"",Plan!B18) | D21: =IF(ISBLANK(Plan!C18),"",Plan!C18) | E21: =IF(ISBLANK(Plan!B18),"",IF(Plan!R18>0,Plan!R18,""))
C22: =IF(ISBLANK(Plan!B19),"",Plan!B19) -> Requisitos | D22: =IF(ISBLANK(Plan!C19),"",Plan!C19) -> Obtener Historias de Usuario (US) | E22: =IF(ISBLANK(Plan!B19),"",IF(Plan!R19>0,Plan!R19,""))
C23: =IF(ISBLANK(Plan!B20),"",Plan!B20) -> Requisitos | D23: =IF(ISBLANK(Plan!C20),"",Plan!C20) -> Describir las US según plantilla (Como/Quiero/Para + criterios de aceptación) | E23: =IF(ISBLANK(Plan!B20),"",IF(Plan!R20>0,Plan!R20,""))
C24: =IF(ISBLANK(Plan!B21),"",Plan!B21) -> Requisitos | D24: =IF(ISBLANK(Plan!C21),"",Plan!C21) -> Completar campos de US para puntos de función | E24: =IF(ISBLANK(Plan!B21),"",IF(Plan!R21>0,Plan!R21,""))
C25: =IF(ISBLANK(Plan!B22),"",Plan!B22) -> Requisitos | D25: =IF(ISBLANK(Plan!C22),"",Plan!C22) -> Elaborar Product Backlog priorizado | E25: =IF(ISBLANK(Plan!B22),"",IF(Plan!R22>0,Plan!R22,""))
C26: =IF(ISBLANK(Plan!B23),"",Plan!B23) -> Requisitos | D26: =IF(ISBLANK(Plan!C23),"",Plan!C23) -> Inspeccionar las US y criterios de aceptacion (Q) | E26: =IF(ISBLANK(Plan!B23),"",IF(Plan!R23>0,Plan!R23,""))
C27: =IF(ISBLANK(Plan!B24),"",Plan!B24) -> Requisitos | D27: =IF(ISBLANK(Plan!C24),"",Plan!C24) -> Poner en línea base las US (GCS) | E27: =IF(ISBLANK(Plan!B24),"",IF(Plan!R24>0,Plan!R24,""))
C28: =IF(ISBLANK(Plan!B25),"",Plan!B25) -> Requisitos | D28: =IF(ISBLANK(Plan!C25),"",Plan!C25) -> Introducir datos de Planificación/Monitorización(esfuerzo real / semana) S3 | E28: =IF(ISBLANK(Plan!B25),"",IF(Plan!R25>0,Plan!R25,""))
C29: =IF(ISBLANK(Plan!B26),"",Plan!B26) -> Requisitos | D29: =IF(ISBLANK(Plan!C26),"",Plan!C26) -> Registrar datos de calidad S3 | E29: =IF(ISBLANK(Plan!B26),"",IF(Plan!R26>0,Plan!R26,""))
... C49: =IF(ISBLANK(Plan!B46),"",Plan!B46) -> Planificación | D49: =IF(ISBLANK(Plan!C46),"",Plan!C46) -> Realizar Diagrama de Gantt del Sprint 1 | E49: =IF(ISBLANK(Plan!B46),"",IF(Plan!R46>0,Plan!R46,""))
C50: =IF(ISBLANK(Plan!#REF!),"",Plan!#REF!) -> #REF! | D50: =IF(ISBLANK(Plan!#REF!),"",Plan!#REF!) -> #REF! | E50: =IF(ISBLANK(Plan!#REF!),"",IF(Plan!#REF!>0,Plan!#REF!,"")) -> #REF!
C51: =IF(ISBLANK(Plan!B47),"",Plan!B47) -> Planificación | D51: =IF(ISBLANK(Plan!C47),"",Plan!C47) -> Inspeccionar planes (Q) y poner en línea base (GCS) | E51: =IF(ISBLANK(Plan!B47),"",IF(Plan!R47>0,Plan!R47,""))
C52: =IF(ISBLANK(Plan!B48),"",Plan!B48) -> Planificación | D52: =IF(ISBLANK(Plan!C48),"",Plan!C48) -> Introducir datos de Planificación/Monitorización S5 (esfuerzo real / semana) | E52: =IF(ISBLANK(Plan!B48),"",IF(Plan!R48>0,Plan!R48,""))
C53: =IF(ISBLANK(Plan!B49),"",Plan!B49) -> Planificación | D53: =IF(ISBLANK(Plan!C49),"",Plan!C49) -> Registrar datos de calidad S5: revisiones, pruebas y defectos | E53: =IF(ISBLANK(Plan!B49),"",IF(Plan!R49>0,Plan!R49,""))
C54: =IF(ISBLANK(Plan!B50),"",Plan!B50) | D54: =IF(ISBLANK(Plan!C50),"",Plan!C50) | E54: =IF(ISBLANK(Plan!B50),"",IF(Plan!R50>0,Plan!R50,""))
C55: =IF(ISBLANK(Plan!B51),"",Plan!B51) | D55: =IF(ISBLANK(Plan!C51),"",Plan!C51) | E55: =IF(ISBLANK(Plan!B51),"",IF(Plan!R51>0,Plan!R51,""))
C56: =IF(ISBLANK(Plan!B52),"",Plan!B52) -> Diseño | D56: =IF(ISBLANK(Plan!C52),"",Plan!C52) -> Realizar diagramas de Casos de Uso | E56: =IF(ISBLANK(Plan!B52),"",IF(Plan!R52>0,Plan!R52,""))
C57: =IF(ISBLANK(Plan!B53),"",Plan!B53) -> Diseño | D57: =IF(ISBLANK(Plan!C53),"",Plan!C53) -> Realizar modelo Entidad/Relación y BBDD | E57: =IF(ISBLANK(Plan!B53),"",IF(Plan!R53>0,Plan!R53,""))
C58: =IF(ISBLANK(Plan!B54),"",Plan!B54) -> Diseño | D58: =IF(ISBLANK(Plan!C54),"",Plan!C54) -> Diseñar pantallas | E58: =IF(ISBLANK(Plan!B54),"",IF(Plan!R54>0,Plan!R54,""))
C59: =IF(ISBLANK(Plan!B55),"",Plan!B55) -> Diseño | D59: =IF(ISBLANK(Plan!C55),"",Plan!C55) -> Inspeccionar diseño (Q) y poner en línea base (GCS) | E59: =IF(ISBLANK(Plan!B55),"",IF(Plan!R55>0,Plan!R55,""))
C60: =IF(ISBLANK(Plan!B56),"",Plan!B56) -> Diseño | D60: =IF(ISBLANK(Plan!C56),"",Plan!C56) -> Introducir datos de Planificación/Monitorización S6 (esfuerzo real / semana, US) | E60: =IF(ISBLANK(Plan!B56),"",IF(Plan!R56>0,Plan!R56,""))
C61: =IF(ISBLANK(Plan!B57),"",Plan!B57) | D61: =IF(ISBLANK(Plan!C57),"",Plan!C57) | E61: =IF(ISBLANK(Plan!B57),"",IF(Plan!R57>0,Plan!R57,""))
C62: =IF(ISBLANK(Plan!B58),"",Plan!B58) | D62: =IF(ISBLANK(Plan!C58),"",Plan!C58) | E62: =IF(ISBLANK(Plan!B58),"",IF(Plan!R58>0,Plan!R58,""))
... C73: =IF(ISBLANK(Plan!B69),"",Plan!B69) -> Implementación | D73: =IF(ISBLANK(Plan!C69),"",Plan!C69) -> Registrar datos de calidad S7: ejecucion, defectos y verificacion DoD | E73: =IF(ISBLANK(Plan!B69),"",IF(Plan!R69>0,Plan!R69,""))
C74: =IF(ISBLANK(Plan!#REF!),"",Plan!#REF!) -> #REF! | D74: =IF(ISBLANK(Plan!#REF!),"",Plan!#REF!) -> #REF! | E74: =IF(ISBLANK(Plan!#REF!),"",IF(Plan!#REF!>0,Plan!#REF!,"")) -> #REF!
C75: =IF(ISBLANK(Plan!B70),"",Plan!B70) | D75: =IF(ISBLANK(Plan!C70),"",Plan!C70) | E75: =IF(ISBLANK(Plan!B70),"",IF(Plan!R70>0,Plan!R70,""))
C76: =IF(ISBLANK(Plan!B71),"",Plan!B71) | D76: =IF(ISBLANK(Plan!C71),"",Plan!C71) | E76: =IF(ISBLANK(Plan!B71),"",IF(Plan!R71>0,Plan!R71,""))
C77: =IF(ISBLANK(Plan!B72),"",Plan!B72) -> Pruebas | D77: =IF(ISBLANK(Plan!C72),"",Plan!C72) -> Definir casos de prueba unitarios y de aceptación por US | E77: =IF(ISBLANK(Plan!B72),"",IF(Plan!R72>0,Plan!R72,""))
C78: =IF(ISBLANK(Plan!B73),"",Plan!B73) -> Pruebas | D78: =IF(ISBLANK(Plan!C73),"",Plan!C73) -> Ejecutar pruebas y registrar resultado esperado vs real y version | E78: =IF(ISBLANK(Plan!B73),"",IF(Plan!R73>0,Plan!R73,""))
C79: =IF(ISBLANK(Plan!B74),"",Plan!B74) -> Pruebas | D79: =IF(ISBLANK(Plan!C74),"",Plan!C74) -> Inspeccionar registros de pruebas, enlazar evidencias y poner en linea base (Q/GCS) | E79: =IF(ISBLANK(Plan!B74),"",IF(Plan!R74>0,Plan!R74,""))
C80: =IF(ISBLANK(Plan!B75),"",Plan!B75) -> Pruebas | D80: =IF(ISBLANK(Plan!C75),"",Plan!C75) -> Introducir datos de Planificación/Monitorización S8 (esfuerzo real / semana, US) | E80: =IF(ISBLANK(Plan!B75),"",IF(Plan!R75>0,Plan!R75,""))
C81: =IF(ISBLANK(Plan!B76),"",Plan!B76) | D81: =IF(ISBLANK(Plan!C76),"",Plan!C76) | E81: =IF(ISBLANK(Plan!B76),"",IF(Plan!R76>0,Plan!R76,""))
C82: =IF(ISBLANK(Plan!B77),"",Plan!B77) | D82: =IF(ISBLANK(Plan!C77),"",Plan!C77) | E82: =IF(ISBLANK(Plan!B77),"",IF(Plan!R77>0,Plan!R77,""))
C83: =IF(ISBLANK(Plan!B78),"",Plan!B78) -> Retrospectiva | D83: =IF(ISBLANK(Plan!C78),"",Plan!C78) -> Realizar informe de retrospectiva del Sprint 1 | E83: =IF(ISBLANK(Plan!B78),"",IF(Plan!R78>0,Plan!R78,""))
C84: =IF(ISBLANK(Plan!B79),"",Plan!B79) -> Retrospectiva | D84: =IF(ISBLANK(Plan!C79),"",Plan!C79) -> Evaluar roles y equipo del Sprint 1 | E84: =IF(ISBLANK(Plan!B79),"",IF(Plan!R79>0,Plan!R79,""))
C85: =IF(ISBLANK(Plan!B80),"",Plan!B80) -> Retrospectiva | D85: =IF(ISBLANK(Plan!C80),"",Plan!C80) -> Revisar productos y procesos; dificultades, PF y PD | E85: =IF(ISBLANK(Plan!B80),"",IF(Plan!R80>0,Plan!R80,""))
C86: =IF(ISBLANK(Plan!B81),"",Plan!B81) -> Retrospectiva | D86: =IF(ISBLANK(Plan!C81),"",Plan!C81) -> Retrospectiva STARFISH (Keep / More / Start / Stop / Less) | E86: =IF(ISBLANK(Plan!B81),"",IF(Plan!R81>0,Plan!R81,""))
... C88: =IF(ISBLANK(Plan!B83),"",Plan!B83) -> Retrospectiva | D88: =IF(ISBLANK(Plan!C83),"",Plan!C83) -> Lecciones aprendidas y mejoras al proceso | E88: =IF(ISBLANK(Plan!B83),"",IF(Plan!R83>0,Plan!R83,""))

Sheet Horas Estimadas
I6: Carga de horas estimadas por rol/semana
J8: Total | K8: 1 | L8: 2 | M8: 3 | N8: 4 | O8: 5 | P8: 6 | Q8: 7 | R8: 8 | S8: 9
I9: Líder / Scrum Master | J9: =SUM(K9:S9) -> 33 | K9: =SUMIFS(Plan!$D$5:$D$83,Plan!$L$5:$L$83,K$8)/60 -> 3.25 | L9: =SUMIFS(Plan!$D$5:$D$83,Plan!$L$5:$L$83,L$8)/60 -> 0.41666667 | M9: =SUMIFS(Plan!$D$5:$D$83,Plan!$L$5:$L$83,M$8)/60 -> 0.83333333 | N9: =SUMIFS(Plan!$D$5:$D$83,Plan!$L$5:$L$83,N$8)/60 -> 3.75 | O9: =SUMIFS(Plan!$D$5:$D$83,Plan!$L$5:$L$83,O$8)/60 -> 0.91666667 | P9: =SUMIFS(Plan!$D$5:$D$83,Plan!$L$5:$L$83,P$8)/60 -> 0.75 | Q9: =SUMIFS(Plan!$D$5:$D$83,Plan!$L$5:$L$83,Q$8)/60 -> 14.083333 | R9: =SUMIFS(Plan!$D$5:$D$83,Plan!$L$5:$L$83,R$8)/60 -> 4.5833333 | S9: =SUMIFS(Plan!$D$5:$D$83,Plan!$L$5:$L$83,S$8)/60 -> 4.4166667
I10: Product Owner | J10: =SUM(K10:S10) -> 32.833333 | K10: =SUMIFS(Plan!$E$5:$E$83,Plan!$L$5:$L$83,K$8)/60 -> 3 | L10: =SUMIFS(Plan!$E$5:$E$83,Plan!$L$5:$L$83,L$8)/60 -> 0.41666667 | M10: =SUMIFS(Plan!$E$5:$E$83,Plan!$L$5:$L$83,M$8)/60 -> 6 | N10: =SUMIFS(Plan!$E$5:$E$83,Plan!$L$5:$L$83,N$8)/60 -> 1.1666667 | O10: =SUMIFS(Plan!$E$5:$E$83,Plan!$L$5:$L$83,O$8)/60 -> 1.25 | P10: =SUMIFS(Plan!$E$5:$E$83,Plan!$L$5:$L$83,P$8)/60 -> 0.91666667 | Q10: =SUMIFS(Plan!$E$5:$E$83,Plan!$L$5:$L$83,Q$8)/60 -> 14.083333 | R10: =SUMIFS(Plan!$E$5:$E$83,Plan!$L$5:$L$83,R$8)/60 -> 4.5833333 | S10: =SUMIFS(Plan!$E$5:$E$83,Plan!$L$5:$L$83,S$8)/60 -> 1.4166667
I11: Planificación | J11: =SUM(K11:S11) -> 30.25 | K11: =SUMIFS(Plan!$F$5:$F$83,Plan!$L$5:$L$83,K$8)/60 -> 2.6666667 | L11: =SUMIFS(Plan!$F$5:$F$83,Plan!$L$5:$L$83,L$8)/60 -> 0.41666667 | M11: =SUMIFS(Plan!$F$5:$F$83,Plan!$L$5:$L$83,M$8)/60 -> 1 | N11: =SUMIFS(Plan!$F$5:$F$83,Plan!$L$5:$L$83,N$8)/60 -> 3.9166667 | O11: =SUMIFS(Plan!$F$5:$F$83,Plan!$L$5:$L$83,O$8)/60 -> 1.25 | P11: =SUMIFS(Plan!$F$5:$F$83,Plan!$L$5:$L$83,P$8)/60 -> 0.91666667 | Q11: =SUMIFS(Plan!$F$5:$F$83,Plan!$L$5:$L$83,Q$8)/60 -> 14.083333 | R11: =SUMIFS(Plan!$F$5:$F$83,Plan!$L$5:$L$83,R$8)/60 -> 4.5833333 | S11: =SUMIFS(Plan!$F$5:$F$83,Plan!$L$5:$L$83,S$8)/60 -> 1.4166667
I12: Desarrollo | J12: =SUM(K12:S12) -> 34.75 | K12: =SUMIFS(Plan!$G$5:$G$83,Plan!$L$5:$L$83,K$8)/60 -> 2.6666667 | L12: =SUMIFS(Plan!$G$5:$G$83,Plan!$L$5:$L$83,L$8)/60 -> 0.41666667 | M12: =SUMIFS(Plan!$G$5:$G$83,Plan!$L$5:$L$83,M$8)/60 -> 3 | N12: =SUMIFS(Plan!$G$5:$G$83,Plan!$L$5:$L$83,N$8)/60 -> 1.4166667 | O12: =SUMIFS(Plan!$G$5:$G$83,Plan!$L$5:$L$83,O$8)/60 -> 4.25 | P12: =SUMIFS(Plan!$G$5:$G$83,Plan!$L$5:$L$83,P$8)/60 -> 2.9166667 | Q12: =SUMIFS(Plan!$G$5:$G$83,Plan!$L$5:$L$83,Q$8)/60 -> 14.083333 | R12: =SUMIFS(Plan!$G$5:$G$83,Plan!$L$5:$L$83,R$8)/60 -> 4.5833333 | S12: =SUMIFS(Plan!$G$5:$G$83,Plan!$L$5:$L$83,S$8)/60 -> 1.4166667
I13: Cambios | J13: =SUM(K13:S13) -> 2.6666667 | K13: =SUMIFS(Plan!$H$5:$H$83,Plan!$L$5:$L$83,K$8)/60 -> 2.6666667 | L13: =SUMIFS(Plan!$H$5:$H$83,Plan!$L$5:$L$83,L$8)/60 -> 0 | M13: =SUMIFS(Plan!$H$5:$H$83,Plan!$L$5:$L$83,M$8)/60 -> 0 | N13: =SUMIFS(Plan!$H$5:$H$83,Plan!$L$5:$L$83,N$8)/60 -> 0 | O13: =SUMIFS(Plan!$H$5:$H$83,Plan!$L$5:$L$83,O$8)/60 -> 0 | P13: =SUMIFS(Plan!$H$5:$H$83,Plan!$L$5:$L$83,P$8)/60 -> 0 | Q13: =SUMIFS(Plan!$H$5:$H$83,Plan!$L$5:$L$83,Q$8)/60 -> 0 | R13: =SUMIFS(Plan!$H$5:$H$83,Plan!$L$5:$L$83,R$8)/60 -> 0 | S13: =SUMIFS(Plan!$H$5:$H$83,Plan!$L$5:$L$83,S$8)/60 -> 0
I14: Calidad | J14: =SUM(K14:S14) -> 2.6666667 | K14: =SUMIFS(Plan!$I$5:$I$83,Plan!$L$5:$L$83,K$8)/60 -> 2.6666667 | L14: =SUMIFS(Plan!$I$5:$I$83,Plan!$L$5:$L$83,L$8)/60 -> 0 | M14: =SUMIFS(Plan!$I$5:$I$83,Plan!$L$5:$L$83,M$8)/60 -> 0 | N14: =SUMIFS(Plan!$I$5:$I$83,Plan!$L$5:$L$83,N$8)/60 -> 0 | O14: =SUMIFS(Plan!$I$5:$I$83,Plan!$L$5:$L$83,O$8)/60 -> 0 | P14: =SUMIFS(Plan!$I$5:$I$83,Plan!$L$5:$L$83,P$8)/60 -> 0 | Q14: =SUMIFS(Plan!$I$5:$I$83,Plan!$L$5:$L$83,Q$8)/60 -> 0 | R14: =SUMIFS(Plan!$I$5:$I$83,Plan!$L$5:$L$83,R$8)/60 -> 0 | S14: =SUMIFS(Plan!$I$5:$I$83,Plan!$L$5:$L$83,S$8)/60 -> 0
I16: IMPORTANTE
I17: ¡ NO EDITAR ESTA PÁGINA ! Se genera automaticamente
I23: Carga de horas estimadas por fase
I25: Fase | J25: Horas
I26: Lanzamiento | J26: =SUMIFS(Plan!$J$5:$J$83,Plan!$B$5:$B$83,I26)/60 -> 16.916667
I27: Requisitos | J27: =SUMIFS(Plan!$J$5:$J$83,Plan!$B$5:$B$83,I27)/60 -> 12.5
I28: Estrategia | J28: =SUMIFS(Plan!$J$5:$J$83,Plan!$B$5:$B$83,I28)/60 -> 10.25
I29: Planificación | J29: =SUMIFS(Plan!$J$5:$J$83,Plan!$B$5:$B$83,I29)/60 -> 7.6666667
I30: Diseño | J30: =SUMIFS(Plan!$J$5:$J$83,Plan!$B$5:$B$83,I30)/60 -> 5.5
I31: Implementación | J31: =SUMIFS(Plan!$J$5:$J$83,Plan!$B$5:$B$83,I31)/60 -> 56.333333
I32: Pruebas | J32: =SUMIFS(Plan!$J$5:$J$83,Plan!$B$5:$B$83,I32)/60 -> 18.333333
I33: Retrospectiva | J33: =SUMIFS(Plan!$J$5:$J$83,Plan!$B$5:$B$83,I33)/60 -> 8.6666667
I35: Total | J35: =SUM(J26:J33) -> 136.16667

Sheet Horas Reales
I6: Carga de horas reales por rol/semana
J8: Total | K8: 1 | L8: 2 | M8: 3 | N8: 4 | O8: 5 | P8: 6 | Q8: 7 | R8: 8 | S8: 9
I9: Líder / Scrum Master | J9: =SUM(K9:S9) -> 9.5833333 | K9: =SUMIFS(Plan!$M$5:$M$83,Plan!$U$5:$U$83,K$8)/60 -> 1.5 | L9: =SUMIFS(Plan!$M$5:$M$83,Plan!$U$5:$U$83,L$8)/60 -> 2.75 | M9: =SUMIFS(Plan!$M$5:$M$83,Plan!$U$5:$U$83,M$8)/60 -> 1.4166667 | N9: =SUMIFS(Plan!$M$5:$M$83,Plan!$U$5:$U$83,N$8)/60 -> 1.75 | O9: =SUMIFS(Plan!$M$5:$M$83,Plan!$U$5:$U$83,O$8)/60 -> 2.1666667 | P9: =SUMIFS(Plan!$M$5:$M$83,Plan!$U$5:$U$83,P$8)/60 -> 0 | Q9: =SUMIFS(Plan!$M$5:$M$83,Plan!$U$5:$U$83,Q$8)/60 -> 0 | R9: =SUMIFS(Plan!$M$5:$M$83,Plan!$U$5:$U$83,R$8)/60 -> 0 | S9: =SUMIFS(Plan!$M$5:$M$83,Plan!$U$5:$U$83,S$8)/60 -> 0
I10: Product Owner | J10: =SUM(K10:S10) -> 10.833333 | K10: =SUMIFS(Plan!$N$5:$N$83,Plan!$U$5:$U$83,K$8)/60 -> 1.5 | L10: =SUMIFS(Plan!$N$5:$N$83,Plan!$U$5:$U$83,L$8)/60 -> 0.75 | M10: =SUMIFS(Plan!$N$5:$N$83,Plan!$U$5:$U$83,M$8)/60 -> 0.75 | N10: =SUMIFS(Plan!$N$5:$N$83,Plan!$U$5:$U$83,N$8)/60 -> 2.5 | O10: =SUMIFS(Plan!$N$5:$N$83,Plan!$U$5:$U$83,O$8)/60 -> 5 | P10: =SUMIFS(Plan!$N$5:$N$83,Plan!$U$5:$U$83,P$8)/60 -> 0.33333333 | Q10: =SUMIFS(Plan!$N$5:$N$83,Plan!$U$5:$U$83,Q$8)/60 -> 0 | R10: =SUMIFS(Plan!$N$5:$N$83,Plan!$U$5:$U$83,R$8)/60 -> 0 | S10: =SUMIFS(Plan!$N$5:$N$83,Plan!$U$5:$U$83,S$8)/60 -> 0
I11: Planificación | J11: =SUM(K11:S11) -> 7.3333333 | K11: =SUMIFS(Plan!$O$5:$O$83,Plan!$U$5:$U$83,K$8)/60 -> 1.4166667 | L11: =SUMIFS(Plan!$O$5:$O$83,Plan!$U$5:$U$83,L$8)/60 -> 0.25 | M11: =SUMIFS(Plan!$O$5:$O$83,Plan!$U$5:$U$83,M$8)/60 -> 0.75 | N11: =SUMIFS(Plan!$O$5:$O$83,Plan!$U$5:$U$83,N$8)/60 -> 1.75 | O11: =SUMIFS(Plan!$O$5:$O$83,Plan!$U$5:$U$83,O$8)/60 -> 0.83333333 | P11: =SUMIFS(Plan!$O$5:$O$83,Plan!$U$5:$U$83,P$8)/60 -> 2.3333333 | Q11: =SUMIFS(Plan!$O$5:$O$83,Plan!$U$5:$U$83,Q$8)/60 -> 0 | R11: =SUMIFS(Plan!$O$5:$O$83,Plan!$U$5:$U$83,R$8)/60 -> 0 | S11: =SUMIFS(Plan!$O$5:$O$83,Plan!$U$5:$U$83,S$8)/60 -> 0
I12: Desarrollo | J12: =SUM(K12:S12) -> 17.083333 | K12: =SUMIFS(Plan!$P$5:$P$83,Plan!$U$5:$U$83,K$8)/60 -> 1.4166667 | L12: =SUMIFS(Plan!$P$5:$P$83,Plan!$U$5:$U$83,L$8)/60 -> 0.25 | M12: =SUMIFS(Plan!$P$5:$P$83,Plan!$U$5:$U$83,M$8)/60 -> 0.75 | N12: =SUMIFS(Plan!$P$5:$P$83,Plan!$U$5:$U$83,N$8)/60 -> 4.75 | O12: =SUMIFS(Plan!$P$5:$P$83,Plan!$U$5:$U$83,O$8)/60 -> 6.5833333 | P12: =SUMIFS(Plan!$P$5:$P$83,Plan!$U$5:$U$83,P$8)/60 -> 3.3333333 | Q12: =SUMIFS(Plan!$P$5:$P$83,Plan!$U$5:$U$83,Q$8)/60 -> 0 | R12: =SUMIFS(Plan!$P$5:$P$83,Plan!$U$5:$U$83,R$8)/60 -> 0 | S12: =SUMIFS(Plan!$P$5:$P$83,Plan!$U$5:$U$83,S$8)/60 -> 0
I13: Cambios | J13: =SUM(K13:S13) -> 1.4166667 | K13: =SUMIFS(Plan!$Q$5:$Q$83,Plan!$U$5:$U$83,K$8)/60 -> 1.25 | L13: =SUMIFS(Plan!$Q$5:$Q$83,Plan!$U$5:$U$83,L$8)/60 -> 0.16666667 | M13: =SUMIFS(Plan!$Q$5:$Q$83,Plan!$U$5:$U$83,M$8)/60 -> 0 | N13: =SUMIFS(Plan!$Q$5:$Q$83,Plan!$U$5:$U$83,N$8)/60 -> 0 | O13: =SUMIFS(Plan!$Q$5:$Q$83,Plan!$U$5:$U$83,O$8)/60 -> 0 | P13: =SUMIFS(Plan!$Q$5:$Q$83,Plan!$U$5:$U$83,P$8)/60 -> 0 | Q13: =SUMIFS(Plan!$Q$5:$Q$83,Plan!$U$5:$U$83,Q$8)/60 -> 0 | R13: =SUMIFS(Plan!$Q$5:$Q$83,Plan!$U$5:$U$83,R$8)/60 -> 0 | S13: =SUMIFS(Plan!$Q$5:$Q$83,Plan!$U$5:$U$83,S$8)/60 -> 0
I14: Calidad | J14: =SUM(K14:S14) -> 1.6666667 | K14: =SUMIFS(Plan!$R$5:$R$83,Plan!$U$5:$U$83,K$8)/60 -> 1.1666667 | L14: =SUMIFS(Plan!$R$5:$R$83,Plan!$U$5:$U$83,L$8)/60 -> 0.5 | M14: =SUMIFS(Plan!$R$5:$R$83,Plan!$U$5:$U$83,M$8)/60 -> 0 | N14: =SUMIFS(Plan!$R$5:$R$83,Plan!$U$5:$U$83,N$8)/60 -> 0 | O14: =SUMIFS(Plan!$R$5:$R$83,Plan!$U$5:$U$83,O$8)/60 -> 0 | P14: =SUMIFS(Plan!$R$5:$R$83,Plan!$U$5:$U$83,P$8)/60 -> 0 | Q14: =SUMIFS(Plan!$R$5:$R$83,Plan!$U$5:$U$83,Q$8)/60 -> 0 | R14: =SUMIFS(Plan!$R$5:$R$83,Plan!$U$5:$U$83,R$8)/60 -> 0 | S14: =SUMIFS(Plan!$R$5:$R$83,Plan!$U$5:$U$83,S$8)/60 -> 0
I15: IMPORTANTE
I16: ¡ NO EDITAR ESTA PÁGINA ! Se genera automaticamente
I23: Carga de horas reales por fase
I25: Fase | J25: Horas
I26: Lanzamiento | J26: =SUMIFS(Plan!$S$5:$S$83,Plan!$B$5:$B$83,I26)/60 -> 13.583333
I27: Requisitos | J27: =SUMIFS(Plan!$S$5:$S$83,Plan!$B$5:$B$83,I27)/60 -> 15.583333
I28: Estrategia | J28: =SUMIFS(Plan!$S$5:$S$83,Plan!$B$5:$B$83,I28)/60 -> 10.5
I29: Planificación | J29: =SUMIFS(Plan!$S$5:$S$83,Plan!$B$5:$B$83,I29)/60 -> 7.4166667
I30: Diseño | J30: =SUMIFS(Plan!$S$5:$S$83,Plan!$B$5:$B$83,I30)/60 -> 2.8333333
I31: Implementación | J31: =SUMIFS(Plan!$S$5:$S$83,Plan!$B$5:$B$83,I31)/60 -> 0
I32: Pruebas | J32: =SUMIFS(Plan!$S$5:$S$83,Plan!$B$5:$B$83,I32)/60 -> 0
I33: Retrospectiva | J33: =SUMIFS(Plan!$S$5:$S$83,Plan!$B$5:$B$83,I33)/60 -> 0
I35: Total | J35: =SUM(J26:J33) -> 49.916667

Sheet Valor Ganado
A1: Análisis de Valor Ganado (EVM) por semana
A2: Unidad de medida: horas de esfuerzo del equipo. PV y EV usan minutos estimados (Plan!I); AC usa minutos reales totales (Plan!Q).
A3: Semana de corte | B3: =IF(COUNT(Plan!$U$5:$U$83)=0,1,MAX(Plan!$U$5:$U$83)) -> 6 | C3: Celda editable: cambia este número (1-9) para ver los indicadores a esa semana. Por defecto usa la última Semana Fin informada.
A4: El valor ganado (EV) solo cuenta actividades con Estado = "Completada". Las "Retrasada" o sin estado no aportan EV (sí pueden aportar AC si tienen minutos reales y Semana Fin).
A6: Indicadores en la semana de corte
A7: BAC (horas plan total) | C7: PV acumulado | E7: EV acumulado | G7: AC acumulado | I7: % completado (EV/BAC)
A8: =SUM(Plan!J:J)/60 -> 136.16667 | C8: =IFERROR(INDEX($E$20:$E$28,MATCH($B$3,$A$20:$A$28,0)),"") -> 52.833333 | E8: =IFERROR(INDEX($F$20:$F$28,MATCH($B$3,$A$20:$A$28,0)),"") -> 47.5 | G8: =IFERROR(INDEX($G$20:$G$28,MATCH($B$3,$A$20:$A$28,0)),"") -> 47.916667 | I8: =IFERROR(E8/A8,"") -> 0.34883721
A9: SV (EV − PV) | C9: CV (EV − AC) | E9: SPI (EV / PV) | G9: CPI (EV / AC) | I9: % gastado (AC/BAC)
A10: =IFERROR(E8-C8,"") -> -5.3333333 | C10: =IFERROR(E8-G8,"") -> -0.41666667 | E10: =IFERROR(IF(C8=0,"",E8/C8),"") -> 0.89905363 | G10: =IFERROR(IF(G8=0,"",E8/G8),"") -> 0.99130435 | I10: =IFERROR(G8/A8,"") -> 0.35189718
A11: EAC (BAC / CPI) | C11: ETC (EAC − AC) | E11: VAC (BAC − EAC) | G11: % planificado (PV/BAC) | I11: Semana de corte
A12: =IFERROR(IF(G10="", "", A8/G10),"") -> 137.36111 | C12: =IFERROR(A12-G8,"") -> 89.444444 | E12: =IFERROR(A8-A12,"") -> -1.1944444 | G12: =IFERROR(C8/A8,"") -> 0.3880049 | I12: =$B$3 -> 6
A14: Lectura rápida
A15: =IF(E10="","SPI: sin datos",IF(E10<1,"SPI < 1: el proyecto va retrasado respecto al plan.","SPI ≥ 1: el proyecto va en plazo o adelantado.")) -> SPI < 1: el proyecto va retrasado respecto al plan.
A16: =IF(G10="","CPI: sin datos",IF(G10<1,"CPI < 1: se está consumiendo más esfuerzo del previsto para el trabajo ganado.","CPI ≥ 1: el esfuerzo real es menor o igual que el valor ganado.")) -> CPI < 1: se está consumiendo más esfuerzo del previsto para el trabajo ganado.
A18: Detalle por semana
A19: Semana | B19: PV semanal (h) | C19: EV semanal (h) | D19: AC semanal (h) | E19: PV acum. (h) | F19: EV acum. (h) | G19: AC acum. (h) | H19: SV (h) | I19: CV (h) | J19: SPI | K19: CPI
A20: 1 | B20: =SUMIFS(Plan!$J$5:$J$83,Plan!$L$5:$L$83,$A20)/60 -> 16.916667 | C20: =SUMIFS(Plan!$J$5:$J$83,Plan!$U$5:$U$83,$A20,Plan!$V$5:$V$83,"Completada")/60 -> 7 | D20: =SUMIFS(Plan!$S$5:$S$83,Plan!$U$5:$U$83,$A20)/60 -> 8.25 | E20: =SUMIFS(Plan!$J$5:$J$83,Plan!$L$5:$L$83,"<="&$A20)/60 -> 16.916667 | F20: =SUMIFS(Plan!$J$5:$J$83,Plan!$U$5:$U$83,"<="&$A20,Plan!$V$5:$V$83,"Completada")/60 -> 7 | G20: =SUMIFS(Plan!$S$5:$S$83,Plan!$U$5:$U$83,"<="&$A20)/60 -> 8.25 | H20: =$F20-$E20 -> -9.9166667 | I20: =$F20-$G20 -> -1.25 | J20: =IF($E20=0,"",$F20/$E20) -> 0.4137931 | K20: =IF($G20=0,"",$F20/$G20) -> 0.84848485
A21: 2 | B21: =SUMIFS(Plan!$J$5:$J$83,Plan!$L$5:$L$83,$A21)/60 -> 1.6666667 | C21: =SUMIFS(Plan!$J$5:$J$83,Plan!$U$5:$U$83,$A21,Plan!$V$5:$V$83,"Completada")/60 -> 9.3333333 | D21: =SUMIFS(Plan!$S$5:$S$83,Plan!$U$5:$U$83,$A21)/60 -> 4.6666667 | E21: =SUMIFS(Plan!$J$5:$J$83,Plan!$L$5:$L$83,"<="&$A21)/60 -> 18.583333 | F21: =SUMIFS(Plan!$J$5:$J$83,Plan!$U$5:$U$83,"<="&$A21,Plan!$V$5:$V$83,"Completada")/60 -> 16.333333 | G21: =SUMIFS(Plan!$S$5:$S$83,Plan!$U$5:$U$83,"<="&$A21)/60 -> 12.916667 | H21: =$F21-$E21 -> -2.25 | I21: =$F21-$G21 -> 3.4166667 | J21: =IF($E21=0,"",$F21/$E21) -> 0.87892377 | K21: =IF($G21=0,"",$F21/$G21) -> 1.2645161
A22: 3 | B22: =SUMIFS(Plan!$J$5:$J$83,Plan!$L$5:$L$83,$A22)/60 -> 10.833333 | C22: =SUMIFS(Plan!$J$5:$J$83,Plan!$U$5:$U$83,$A22,Plan!$V$5:$V$83,"Completada")/60 -> 3.25 | D22: =SUMIFS(Plan!$S$5:$S$83,Plan!$U$5:$U$83,$A22)/60 -> 3.6666667 | E22: =SUMIFS(Plan!$J$5:$J$83,Plan!$L$5:$L$83,"<="&$A22)/60 -> 29.416667 | F22: =SUMIFS(Plan!$J$5:$J$83,Plan!$U$5:$U$83,"<="&$A22,Plan!$V$5:$V$83,"Completada")/60 -> 19.583333 | G22: =SUMIFS(Plan!$S$5:$S$83,Plan!$U$5:$U$83,"<="&$A22)/60 -> 16.583333 | H22: =$F22-$E22 -> -9.8333333 | I22: =$F22-$G22 -> 3 | J22: =IF($E22=0,"",$F22/$E22) -> 0.66572238 | K22: =IF($G22=0,"",$F22/$G22) -> 1.1809045
A23: 4 | B23: =SUMIFS(Plan!$J$5:$J$83,Plan!$L$5:$L$83,$A23)/60 -> 10.25 | C23: =SUMIFS(Plan!$J$5:$J$83,Plan!$U$5:$U$83,$A23,Plan!$V$5:$V$83,"Completada")/60 -> 8.6666667 | D23: =SUMIFS(Plan!$S$5:$S$83,Plan!$U$5:$U$83,$A23)/60 -> 10.75 | E23: =SUMIFS(Plan!$J$5:$J$83,Plan!$L$5:$L$83,"<="&$A23)/60 -> 39.666667 | F23: =SUMIFS(Plan!$J$5:$J$83,Plan!$U$5:$U$83,"<="&$A23,Plan!$V$5:$V$83,"Completada")/60 -> 28.25 | G23: =SUMIFS(Plan!$S$5:$S$83,Plan!$U$5:$U$83,"<="&$A23)/60 -> 27.333333 | H23: =$F23-$E23 -> -11.416667 | I23: =$F23-$G23 -> 0.91666667 | J23: =IF($E23=0,"",$F23/$E23) -> 0.71218487 | K23: =IF($G23=0,"",$F23/$G23) -> 1.0335366
A24: 5 | B24: =SUMIFS(Plan!$J$5:$J$83,Plan!$L$5:$L$83,$A24)/60 -> 7.6666667 | C24: =SUMIFS(Plan!$J$5:$J$83,Plan!$U$5:$U$83,$A24,Plan!$V$5:$V$83,"Completada")/60 -> 12.25 | D24: =SUMIFS(Plan!$S$5:$S$83,Plan!$U$5:$U$83,$A24)/60 -> 14.583333 | E24: =SUMIFS(Plan!$J$5:$J$83,Plan!$L$5:$L$83,"<="&$A24)/60 -> 47.333333 | F24: =SUMIFS(Plan!$J$5:$J$83,Plan!$U$5:$U$83,"<="&$A24,Plan!$V$5:$V$83,"Completada")/60 -> 40.5 | G24: =SUMIFS(Plan!$S$5:$S$83,Plan!$U$5:$U$83,"<="&$A24)/60 -> 41.916667 | H24: =$F24-$E24 -> -6.8333333 | I24: =$F24-$G24 -> -1.4166667 | J24: =IF($E24=0,"",$F24/$E24) -> 0.8556338 | K24: =IF($G24=0,"",$F24/$G24) -> 0.96620278
A25: 6 | B25: =SUMIFS(Plan!$J$5:$J$83,Plan!$L$5:$L$83,$A25)/60 -> 5.5 | C25: =SUMIFS(Plan!$J$5:$J$83,Plan!$U$5:$U$83,$A25,Plan!$V$5:$V$83,"Completada")/60 -> 7 | D25: =SUMIFS(Plan!$S$5:$S$83,Plan!$U$5:$U$83,$A25)/60 -> 6 | E25: =SUMIFS(Plan!$J$5:$J$83,Plan!$L$5:$L$83,"<="&$A25)/60 -> 52.833333 | F25: =SUMIFS(Plan!$J$5:$J$83,Plan!$U$5:$U$83,"<="&$A25,Plan!$V$5:$V$83,"Completada")/60 -> 47.5 | G25: =SUMIFS(Plan!$S$5:$S$83,Plan!$U$5:$U$83,"<="&$A25)/60 -> 47.916667 | H25: =$F25-$E25 -> -5.3333333 | I25: =$F25-$G25 -> -0.41666667 | J25: =IF($E25=0,"",$F25/$E25) -> 0.89905363 | K25: =IF($G25=0,"",$F25/$G25) -> 0.99130435
A26: 7 | B26: =SUMIFS(Plan!$J$5:$J$83,Plan!$L$5:$L$83,$A26)/60 -> 56.333333 | C26: =SUMIFS(Plan!$J$5:$J$83,Plan!$U$5:$U$83,$A26,Plan!$V$5:$V$83,"Completada")/60 -> 0 | D26: =SUMIFS(Plan!$S$5:$S$83,Plan!$U$5:$U$83,$A26)/60 -> 0 | E26: =SUMIFS(Plan!$J$5:$J$83,Plan!$L$5:$L$83,"<="&$A26)/60 -> 109.16667 | F26: =SUMIFS(Plan!$J$5:$J$83,Plan!$U$5:$U$83,"<="&$A26,Plan!$V$5:$V$83,"Completada")/60 -> 47.5 | G26: =SUMIFS(Plan!$S$5:$S$83,Plan!$U$5:$U$83,"<="&$A26)/60 -> 47.916667 | H26: =$F26-$E26 -> -61.666667 | I26: =$F26-$G26 -> -0.41666667 | J26: =IF($E26=0,"",$F26/$E26) -> 0.4351145 | K26: =IF($G26=0,"",$F26/$G26) -> 0.99130435
A27: 8 | B27: =SUMIFS(Plan!$J$5:$J$83,Plan!$L$5:$L$83,$A27)/60 -> 18.333333 | C27: =SUMIFS(Plan!$J$5:$J$83,Plan!$U$5:$U$83,$A27,Plan!$V$5:$V$83,"Completada")/60 -> 0 | D27: =SUMIFS(Plan!$S$5:$S$83,Plan!$U$5:$U$83,$A27)/60 -> 0 | E27: =SUMIFS(Plan!$J$5:$J$83,Plan!$L$5:$L$83,"<="&$A27)/60 -> 127.5 | F27: =SUMIFS(Plan!$J$5:$J$83,Plan!$U$5:$U$83,"<="&$A27,Plan!$V$5:$V$83,"Completada")/60 -> 47.5 | G27: =SUMIFS(Plan!$S$5:$S$83,Plan!$U$5:$U$83,"<="&$A27)/60 -> 47.916667 | H27: =$F27-$E27 -> -80 | I27: =$F27-$G27 -> -0.41666667 | J27: =IF($E27=0,"",$F27/$E27) -> 0.37254902 | K27: =IF($G27=0,"",$F27/$G27) -> 0.99130435
A28: 9 | B28: =SUMIFS(Plan!$J$5:$J$83,Plan!$L$5:$L$83,$A28)/60 -> 8.6666667 | C28: =SUMIFS(Plan!$J$5:$J$83,Plan!$U$5:$U$83,$A28,Plan!$V$5:$V$83,"Completada")/60 -> 0 | D28: =SUMIFS(Plan!$S$5:$S$83,Plan!$U$5:$U$83,$A28)/60 -> 0 | E28: =SUMIFS(Plan!$J$5:$J$83,Plan!$L$5:$L$83,"<="&$A28)/60 -> 136.16667 | F28: =SUMIFS(Plan!$J$5:$J$83,Plan!$U$5:$U$83,"<="&$A28,Plan!$V$5:$V$83,"Completada")/60 -> 47.5 | G28: =SUMIFS(Plan!$S$5:$S$83,Plan!$U$5:$U$83,"<="&$A28)/60 -> 47.916667 | H28: =$F28-$E28 -> -88.666667 | I28: =$F28-$G28 -> -0.41666667 | J28: =IF($E28=0,"",$F28/$E28) -> 0.34883721 | K28: =IF($G28=0,"",$F28/$G28) -> 0.99130435
A30: Definiciones
A31: PV — Valor planificado | C31: Esfuerzo estimado de las actividades cuya Semana Estimada es esa semana (o ≤ semana en el acumulado).
A32: EV — Valor ganado | C32: Esfuerzo estimado de las actividades Completadas cuya Semana Fin es esa semana (o ≤ semana en el acumulado).
A33: AC — Coste real | C33: Esfuerzo real (Plan!Q, ya incluye a todos los roles, incluido Líder/SM y Product Owner) de actividades con Semana Fin en esa semana (o ≤ semana).
A34: SV / SPI | C34: Variación e índice de cronograma. SV < 0 o SPI < 1 ⇒ retraso.
A35: CV / CPI | C35: Variación e índice de coste/esfuerzo. CV < 0 o CPI < 1 ⇒ sobrecoste de esfuerzo.
A36: BAC / EAC / ETC / VAC | C36: Presupuesto total; estimación a conclusión (BAC/CPI); esfuerzo que falta (EAC−AC); variación a conclusión (BAC−EAC).

Sheet Historias
A1: Plantilla de historias de usuario y seguimiento para burndown
A2: Rellena o edita las historias. El burndown se calcula solo: una historia deja de contar como pendiente cuando Estado = Hecha y tiene Semana fin. Las celdas amarillas son de entrada.
A4: ID | B4: Épica | C4: Historia de usuario | D4: Criterios de aceptación | E4: Prioridad | F4: Semana plan | G4: Estado | H4: Semana fin | I4: Responsable | J4: Notas
A5: US-01 | B5: Catálogo | C5: Como responsable del almacén, quiero registrar y consultar almacenes para ubicar los vehículos. | D5: Puedo crear, editar y listar almacenes. Los datos se persisten. | E5: Alta | F5: 7 | G5: Hecha | H5: 4 | I5: Cambios / Desarrollo
A6: US-02 | B6: Catálogo | C6: Como gestor, quiero mantener las marcas de vehículos para clasificar el stock. | D6: Alta/edición de marcas. La marca aparece en el alta de vehículo. | E6: Alta | F6: 7 | G6: En curso | I6: Planificación / Calidad
A7: US-03 | B7: Catálogo | C7: Como gestor, quiero dar de alta un vehículo con sus datos principales para incorporarlo al inventario. | D7: Formulario de alta válido. El vehículo queda listado. Campos obligatorios validados. | E7: Alta | F7: 7 | G7: En curso | I7: Planificación / Calidad
A8: US-04 | B8: Configuración | C8: Como gestor, quiero elegir la gamma del vehículo en un desplegable para no escribirla a mano. | D8: Desplegable con gammas vigentes. Valor guardado en el vehículo. | E8: Media | F8: 8 | G8: Pendiente | I8: Cambios / Desarrollo
A9: US-05 | B9: Configuración | C9: Como gestor, quiero seleccionar el tipo de marchas desde un desplegable al dar de alta el vehículo. | D9: Desplegable operativo y persistido. | E9: Media | F9: 8 | G9: Pendiente | I9: Cambios / Desarrollo
A10: US-06 | B10: Configuración | C10: Como gestor, quiero indicar el tipo de techo mediante un desplegable. | D10: Desplegable operativo y persistido. | E10: Media | F10: 8 | G10: Pendiente | I10: Planificación / Calidad
A11: US-07 | B11: Configuración | C11: Como gestor, quiero indicar el número o tipo de puertas mediante un desplegable. | D11: Desplegable operativo y persistido. | E11: Media | F11: 8 | G11: Pendiente | I11: Planificación / Calidad
A12: US-08 | B12: Consulta | C12: Como usuario, quiero listar los coches y filtrarlos para encontrar un vehículo concreto. | D12: Listado con filtros combinables. Resultados coherentes con el alta. | E12: Alta | F12: 8 | G12: Pendiente | I12: Cambios / Desarrollo
A13: US-09 | B13: Calidad | C13: Como equipo, queremos pruebas unitarias de las historias implementadas para asegurar el comportamiento. | D13: PU ejecutadas y registradas sobre las historias Hechas. | E13: Alta | F13: 8 | G13: Pendiente | I13: Todos
A14: US-10 | B14: Calidad | C14: Como equipo, queremos pruebas de integración y de sistema para validar el flujo completo. | D14: PI y PS definidas y ejecutadas. Defectos críticos cerrados. | E14: Alta | F14: 8 | G14: Pendiente | I14: Todos
A15: US-11 | G15: Pendiente
A16: US-12 | G16: Pendiente
A17: US-13 | G17: Pendiente
A18: US-14 | G18: Pendiente
A19: US-15 | G19: Pendiente
A20: US-16 | G20: Pendiente
A21: US-17 | G21: Pendiente
A22: US-18 | G22: Pendiente
A23: US-19 | G23: Pendiente
A24: US-20 | G24: Pendiente
A25: TOTAL
A28: Las US de esta hoja son el Product Backlog (fase Requisitos del CV). Al terminar: inspeccionar (Q) y poner en línea base (GCS).
A29: 1. Añade o edita historias en las filas amarillas (hay 10 filas extra vacías; puedes insertar más copiando una fila de datos).
A31: 3. Cuando una historia termina, pon Estado = Hecha y la Semana fin (1-9). En ese momento las horas restantes pasan a 0 y el burndown baja.
A32: 4. No hace falta tocar la hoja Burndown: se recalcula sola. Si insertas filas, amplía los rangos de las fórmulas del burndown para incluirlas.
A33: 5. Las historias prefijadas salen del alcance de codificación/pruebas del Plan (almacén, marcas, alta, desplegables, listado y pruebas). Cámbialas si tu producto es otro.

Sheet Burndown
A1: Burndown del proyecto
A2: Ideal = reparto lineal del total entre las semanas del horizonte. Real = lo que sigue pendiente al cierre de cada semana (historias no Hechas o Hechas después de esa semana).
A4: Configuración
A5: Semanas del horizonte | B5: 9 | C5: Cambia 9 si tu proyecto tiene otro número de sprints/semanas.
A6: Semana actual | B6: =IF(COUNT(Historias!H5:H24)=0,1,MAX(Historias!H5:H24)) -> 4 | C6: Editable. Por defecto, la última Semana fin informada en Historias.
A8: Estado del proyecto
A9: Horas totales | C9: Horas restantes | E9: Horas quemadas | G9: % horas hechas
A10: =SUM(Plan!J:J)/60 -> 136.16667 | C10: =A10-E10 -> 88.666667 | E10: =SUMIF(Plan!V:V,"Completada",Plan!J:J)/60 -> 47.5 | G10: =IF(A10=0,"",E10/A10) -> 0.34883721
A11: Historias escritas | C11: Historias hechas | E11: En curso | G11: Velocidad (horas quemadas / sem. actual)
A12: =COUNTA(Historias!C5:C24) -> 10 | C12: =COUNTIF(Historias!G5:G24,"Hecha") -> 1 | E12: =COUNTIF(Historias!G5:G24,"En curso") -> 2 | G12: =IF(OR(B6=0,B6=""),"",E10/B6) -> 11.875
A14: Datos del burndown
A15: Semana | B15: Ideal horas | C15: Restante horas | D15: Quemadas horas
A16: 0 | B16: =$A$10 -> 136.16667 | C16: =$A$10 -> 136.16667 | D16: 0
A17: 1 | B17: =$A$10*(1-A17/$B$5) -> 121.03704 | C17: =$A$10-D17 -> 129.16667 | D17: =SUMIFS(Plan!J:J,Plan!V:V,"Completada",Plan!U:U,"<="&Burndown!A17)/60 -> 7
A18: 2 | B18: =$A$10*(1-A18/$B$5) -> 105.90741 | C18: =$A$10-D18 -> 119.83333 | D18: =SUMIFS(Plan!J:J,Plan!V:V,"Completada",Plan!U:U,"<="&Burndown!A18)/60 -> 16.333333
A19: 3 | B19: =$A$10*(1-A19/$B$5) -> 90.777778 | C19: =$A$10-D19 -> 116.58333 | D19: =SUMIFS(Plan!J:J,Plan!V:V,"Completada",Plan!U:U,"<="&Burndown!A19)/60 -> 19.583333
A20: 4 | B20: =$A$10*(1-A20/$B$5) -> 75.648148 | C20: =$A$10-D20 -> 107.91667 | D20: =SUMIFS(Plan!J:J,Plan!V:V,"Completada",Plan!U:U,"<="&Burndown!A20)/60 -> 28.25
A21: 5 | B21: =$A$10*(1-A21/$B$5) -> 60.518519 | C21: =$A$10-D21 -> 95.666667 | D21: =SUMIFS(Plan!J:J,Plan!V:V,"Completada",Plan!U:U,"<="&Burndown!A21)/60 -> 40.5
A22: 6 | B22: =$A$10*(1-A22/$B$5) -> 45.388889 | C22: =$A$10-D22 -> 88.666667 | D22: =SUMIFS(Plan!J:J,Plan!V:V,"Completada",Plan!U:U,"<="&Burndown!A22)/60 -> 47.5
A23: 7 | B23: =$A$10*(1-A23/$B$5) -> 30.259259 | C23: =$A$10-D23 -> 88.666667 | D23: =SUMIFS(Plan!J:J,Plan!V:V,"Completada",Plan!U:U,"<="&Burndown!A23)/60 -> 47.5
A24: 8 | B24: =$A$10*(1-A24/$B$5) -> 15.12963 | C24: =$A$10-D24 -> 88.666667 | D24: =SUMIFS(Plan!J:J,Plan!V:V,"Completada",Plan!U:U,"<="&Burndown!A24)/60 -> 47.5
A25: 9 | B25: =$A$10*(1-A25/$B$5) -> 0 | C25: =$A$10-D25 -> 88.666667 | D25: =SUMIFS(Plan!J:J,Plan!V:V,"Completada",Plan!U:U,"<="&Burndown!A25)/60 -> 47.5
A27: Previsión
A28: Semanas estimadas para terminar (restante / velocidad) | C28: =IF(OR(G12="",G12=0),"Sin velocidad todavía",C10/G12) -> 7.4666667 | D28: Si la velocidad media se mantiene. Si no hay historias Hechas con Semana fin, no hay velocidad.
A30: Cómo leerlo
A31: Si la línea Real (restante) está por ENCIMA de la Ideal, vais retrasados: os queda más trabajo del que deberíais a esa semana.
A32: Si está por DEBAJO, vais adelantados. La línea Ideal asume ritmo constante hasta la última semana del horizonte.

Sheet Resumen Scrum
A2: Resumen de seguimiento Scrum
A3: Vista de lectura para el profesor y el equipo. Los indicadores se actualizan con Historias, Pruebas, Defectos y DoD.
A5: Sprint consultado | B5: Sprint 1 | D5: Equipo | E5: Completar
A6: Version consultada | B6: v1.0 | D6: Version del plan | E6: 2.13 Scrum
D7: Coordinacion de Calidad | E7: Completar
A9: Indicador | B9: Resultado
A10: Historias escritas | B10: =COUNTA(Historias!$C$5:$C$24) -> 10 | D10: Uso
A11: Historias hechas | B11: =COUNTIF(Historias!$G$5:$G$24,"Hecha") -> 1 | D11: Cambiar B5 y B6 para consultar otro Sprint y version.
A12: Historias en curso | B12: =COUNTIF(Historias!$G$5:$G$24,"En curso") -> 2 | D12: Las celdas amarillas son datos editables.
A13: Puntos Función previstos del Sprint | B13: 51 | D13: El plan original conserva PF, Gantt y Valor Ganado.
A14: Pruebas registradas en la version | B14: =COUNTIFS(Pruebas!$C$7:$C$106,$B$6,Pruebas!$A$7:$A$106,"<>") -> 3 | D14: Una historia solo cumple DoD si tiene las seis condiciones y evidencia.
A15: Pruebas superadas en la version | B15: =COUNTIFS(Pruebas!$C$7:$C$106,$B$6,Pruebas!$N$7:$N$106,"Superada") -> 2 | D15: Registrar las decisiones y acciones en la hoja correspondiente.
A16: Pruebas fallidas en la version | B16: =COUNTIFS(Pruebas!$C$7:$C$106,$B$6,Pruebas!$N$7:$N$106,"Fallida") -> 1
A17: Defectos abiertos en la version | B17: =COUNTIFS(Defectos!$C$7:$C$106,$B$6,Defectos!$J$7:$J$106,"<>Cerrado",Defectos!$D$7:$D$106,"<>") -> 1
A18: Historias que cumplen DoD (todas versiones) | B18: =COUNTIF(DoD!$K$7:$K$106,"Cumple DoD") -> 1
A19: Historias pendientes de DoD (todas versiones) | B19: =COUNTIF(DoD!$K$7:$K$106,"Pendiente") -> 1
A23: Balance y decisiones del Sprint
A25: Controles previstos y realizados
A26: Pendientes que afectan al objetivo
A27: Accion acordada
A28: Responsable y proxima comprobacion
A29: Esfuerzo previsto, real y pendiente
A30: Enlace al acta o decision

Sheet Plan Calidad
A2: Plan de calidad
A3: El plan se acuerda al inicio y se revisa en cada Sprint. Planifica controles y evidencias; no sustituye a los registros de ejecución.
A5: Ejemplo docente inicial. Sustituir el ejemplo por los datos y enlaces del equipo.
A6: Control | B6: Sprint | C6: Alcance | D6: Actividad | E6: Momento | F6: Responsables | G6: Criterio verificable | H6: Evidencia prevista | I6: Estado | J6: Previsto min | K6: Real min | L6: Pendiente min | M6: Observaciones | N6: Momento de uso | O6: Regla docente
A7: C-01 | B7: Sprint 1 | C7: Historias y aceptacion | D7: Revisar historia y criterios | E7: Antes de implementar | F7: Autor + otro integrante | G7: Criterios observables; dudas resueltas | H7: INS_SprintBacklog | I7: Previsto | J7: 30 | K7: 20 | L7: =IF(OR(J7="",K7=""),"",MAX(J7-K7,0)) -> 10 | N7: Planificacion | O7: Asignar responsables y esfuerzo
A8: C-02
A9: C-03
A10: C-04
A11: C-05
A12: C-06
L13: =IF(OR(J13="",K13=""),"",MAX(J13-K13,0))
L14: =IF(OR(J14="",K14=""),"",MAX(J14-K14,0))
L15: =IF(OR(J15="",K15=""),"",MAX(J15-K15,0))
L16: =IF(OR(J16="",K16=""),"",MAX(J16-K16,0))
L17: =IF(OR(J17="",K17=""),"",MAX(J17-K17,0))
L18: =IF(OR(J18="",K18=""),"",MAX(J18-K18,0))
L19: =IF(OR(J19="",K19=""),"",MAX(J19-K19,0))
L20: =IF(OR(J20="",K20=""),"",MAX(J20-K20,0))
L21: =IF(OR(J21="",K21=""),"",MAX(J21-K21,0))
L22: =IF(OR(J22="",K22=""),"",MAX(J22-K22,0))
L23: =IF(OR(J23="",K23=""),"",MAX(J23-K23,0))
L24: =IF(OR(J24="",K24=""),"",MAX(J24-K24,0))
... L106: =IF(OR(J106="",K106=""),"",MAX(J106-K106,0))

Sheet DoD
A2: DoD por historia y version
A3: DoD inicial propuesta: cumplir aceptación, integrar, revisar por otro integrante, ejecutar y registrar pruebas/regresion, actualizar documentación y disponer de versión ejecutable identificada.
A5: Ejemplo docente inicial. Sustituir el ejemplo por los datos y enlaces del equipo.
A6: Sprint | B6: Version producto | C6: Historia | D6: Aceptacion | E6: Integracion | F6: Revision por otro | G6: Pruebas y regresion | H6: Documentacion | I6: Version ejecutable | J6: Indice de evidencias | K6: Resultado | L6: Observaciones
A7: Sprint 1 | B7: v1.0 | C7: US-03 | D7: Cumple | E7: Cumple | F7: Pendiente | G7: Pendiente | H7: Pendiente | I7: Pendiente | J7: Evidencias/E-001 | K7: =IF(C7="","",IF(COUNTIF(D7:I7,"Cumple")=6,IF(J7="","Falta evidencia","Cumple DoD"),"Pendiente")) -> Pendiente | L7: Ejemplo: falta ejecutar aceptación y regresión
A8: Sprint 1 | B8: v1.1 | C8: US-03 | D8: Cumple | E8: Cumple | F8: Cumple | G8: Cumple | H8: Cumple | I8: Cumple | J8: Evidencias/E-004 | K8: =IF(C8="","",IF(COUNTIF(D8:I8,"Cumple")=6,IF(J8="","Falta evidencia","Cumple DoD"),"Pendiente")) -> Cumple DoD | L8: Ejemplo: revisión y pruebas repetidas tras corrección
K9: =IF(C9="","",IF(COUNTIF(D9:I9,"Cumple")=6,IF(J9="","Falta evidencia","Cumple DoD"),"Pendiente"))
K10: =IF(C10="","",IF(COUNTIF(D10:I10,"Cumple")=6,IF(J10="","Falta evidencia","Cumple DoD"),"Pendiente"))
K11: =IF(C11="","",IF(COUNTIF(D11:I11,"Cumple")=6,IF(J11="","Falta evidencia","Cumple DoD"),"Pendiente"))
K12: =IF(C12="","",IF(COUNTIF(D12:I12,"Cumple")=6,IF(J12="","Falta evidencia","Cumple DoD"),"Pendiente"))
K13: =IF(C13="","",IF(COUNTIF(D13:I13,"Cumple")=6,IF(J13="","Falta evidencia","Cumple DoD"),"Pendiente"))
K14: =IF(C14="","",IF(COUNTIF(D14:I14,"Cumple")=6,IF(J14="","Falta evidencia","Cumple DoD"),"Pendiente"))
K15: =IF(C15="","",IF(COUNTIF(D15:I15,"Cumple")=6,IF(J15="","Falta evidencia","Cumple DoD"),"Pendiente"))
K16: =IF(C16="","",IF(COUNTIF(D16:I16,"Cumple")=6,IF(J16="","Falta evidencia","Cumple DoD"),"Pendiente"))
K17: =IF(C17="","",IF(COUNTIF(D17:I17,"Cumple")=6,IF(J17="","Falta evidencia","Cumple DoD"),"Pendiente"))
K18: =IF(C18="","",IF(COUNTIF(D18:I18,"Cumple")=6,IF(J18="","Falta evidencia","Cumple DoD"),"Pendiente"))
K19: =IF(C19="","",IF(COUNTIF(D19:I19,"Cumple")=6,IF(J19="","Falta evidencia","Cumple DoD"),"Pendiente"))
K20: =IF(C20="","",IF(COUNTIF(D20:I20,"Cumple")=6,IF(J20="","Falta evidencia","Cumple DoD"),"Pendiente"))
... K106: =IF(C106="","",IF(COUNTIF(D106:I106,"Cumple")=6,IF(J106="","Falta evidencia","Cumple DoD"),"Pendiente"))

Sheet Pruebas
A2: Pruebas y ejecuciones
A3: Una fila por ejecución. Conservar los fallos al repetir una prueba y añadir una nueva fila para la nueva versión.
A5: Ejemplo docente inicial. Sustituir el ejemplo por los datos y enlaces del equipo.
A6: Ejecucion | B6: Sprint | C6: Version | D6: Historia | E6: Criterio | F6: Prueba | G6: Fecha o corte | H6: Ejecutor | I6: Entorno | J6: Datos iniciales | K6: Pasos | L6: Esperado | M6: Obtenido | N6: Resultado | O6: Defecto | P6: Archivo o enlace
A7: T03-01-v1.0 | B7: Sprint 1 | C7: v1.0 | D7: US-03 | E7: CA03.1 | F7: T03-01 | G7: Corte ejemplo | H7: Integrante B | I7: Aplicacion + BD de prueba | J7: Vehiculo V-042; usuario autenticado | K7: Registrar vehículo con datos válidos | L7: Vehículo persistido y visible en listado | M7: Vehículo persistido y visible en listado | N7: Superada | P7: Evidencias/
A8: T03-02-v1.0 | B8: Sprint 1 | C8: v1.0 | D8: US-03 | E8: CA03.2 | F8: T03-02 | G8: Corte ejemplo | H8: Integrante B | I8: Aplicacion + BD de prueba | J8: Vehiculo V-042; usuario autenticado | K8: Dejar vacío un campo obligatorio | L8: Se muestra validación y no se persiste | M8: Se muestra validación y no se persiste | N8: Superada | P8: Evidencias/
A9: T03-03-v1.0 | B9: Sprint 1 | C9: v1.0 | D9: US-03 | E9: CA03.3 | F9: T03-03 | G9: Corte ejemplo | H9: Integrante B | I9: Aplicacion + BD de prueba | J9: Vehiculo V-042; usuario autenticado | K9: Editar vehículo existente | L9: Cambios persistidos y visibles | M9: Error al guardar cambio | N9: Fallida | O9: D-03 | P9: Evidencias/
A10: T03-01-v1.1 | B10: Sprint 1 | C10: v1.1 | D10: US-03 | E10: CA03.1 | F10: T03-01 | G10: Corte ejemplo | H10: Integrante B | I10: Aplicacion + BD de prueba | J10: Vehiculo V-042; usuario autenticado | K10: Registrar vehículo con datos válidos | L10: Vehículo persistido y visible en listado | M10: Vehículo persistido y visible en listado | N10: Superada | P10: Evidencias/
A11: T03-02-v1.1 | B11: Sprint 1 | C11: v1.1 | D11: US-03 | E11: CA03.2 | F11: T03-02 | G11: Corte ejemplo | H11: Integrante B | I11: Aplicacion + BD de prueba | J11: Vehiculo V-042; usuario autenticado | K11: Dejar vacío un campo obligatorio | L11: Se muestra validación y no se persiste | M11: Se muestra validación y no se persiste | N11: Superada | P11: Evidencias/
A12: T03-03-v1.1 | B12: Sprint 1 | C12: v1.1 | D12: US-03 | E12: CA03.3 | F12: T03-03 | G12: Corte ejemplo | H12: Integrante B | I12: Aplicacion + BD de prueba | J12: Vehiculo V-042; usuario autenticado | K12: Editar vehículo existente | L12: Cambios persistidos y visibles | M12: Cambios persistidos y visibles | N12: Superada | P12: Evidencias/

Sheet Evidencias
A2: Evidencias y revisiones
A3: La evidencia debe permitir identificar qué se revisó o ejecutó, quién participó, sobre qué versión, con qué resultado y qué acción siguió.
A5: Ejemplo docente inicial. Sustituir el ejemplo por los datos y enlaces del equipo.
A6: Registro | B6: Sprint | C6: Version | D6: Control | E6: Historia | F6: Elemento revisado | G6: Fecha o corte | H6: Autor | I6: Revisor | J6: Criterio de revision | K6: Hallazgos | L6: Estado | M6: Accion y verificacion | N6: Archivo o enlace
A7: E-001 | B7: Sprint 1 | C7: v1.0 | D7: C-02 | E7: US-03 | F7: Formulario y persistencia del alta | G7: Corte ejemplo | H7: Integrante A | I7: Integrante B | J7: Campos obligatorios y datos persistidos | K7: Falta prueba de edición | L7: Con hallazgos | M7: Actualizar matriz y programar T03-03 | N7: Evidencias/E-001
A8: E-004 | B8: Sprint 1 | C8: v1.1 | D8: C-06 | E8: US-03 | F8: Checklist DoD de la historia | G8: Cierre Sprint | H8: Equipo | I8: Integrante B | J8: Seis condiciones y enlaces completos | L8: Cerrada | M8: Declarar Done tras comprobar enlaces | N8: Evidencias/E-004

Sheet Defectos
A2: Defectos y acciones
A3: Severidad describe el impacto y prioridad el orden de atención. Un defecto que incumple aceptación o DoD impide declarar terminada la historia afectada.
A5: Ejemplo docente inicial. Sustituir el ejemplo por los datos y enlaces del equipo.
A6: Corte | B6: Sprint | C6: Version | D6: Defecto | E6: Historia | F6: Descripcion | G6: Severidad | H6: Prioridad | I6: Responsable | J6: Estado | K6: Accion o correccion | L6: Fecha o corte objetivo | M6: Verificacion | N6: Archivo o enlace
A7: D03-C1 | B7: Sprint 1 | C7: v1.0 | D7: D-03 | E7: US-03 | F7: La edición no guarda todos los campos | G7: Alta | H7: Antes de Done | I7: Integrante A | J7: Abierto | K7: Revisar actualización y repetir T03-03 | L7: Corte 2 | M7: T03-03 fallida | N7: Defectos/D-03
A8: D03-C2 | B8: Sprint 1 | C8: v1.1 | D8: D-03 | E8: US-03 | F8: La edición no guarda todos los campos | G8: Alta | H8: Antes de Done | I8: Integrante A | J8: Cerrado | K8: Corrección integrada | L8: Cierre | M8: T03-03 superada | N8: Defectos/D-03
